[[2.0e-6,{"Started":[]}],[0.816817,{"FileProcessed":[]}],[1.104144,{"QuickSpecDone":{"eqs":191,"classes":559}}],[1.210511,{"PlainProof":{"prop_name":"map f [] == []","lemmas":[]}}],[1.253078,{"PlainProof":{"prop_name":"take x [] == []","lemmas":[]}}],[1.31944,{"PlainProof":{"prop_name":"take Z xs == []","lemmas":[]}}],[6.41238,{"InductiveProof":{"prop_name":"take x (map f xs) == map f (take x xs)","lemmas":[]}}],[12.469322,{"FailedProof":{"prop_name":"take y (take x xs) == take x (take y xs)"}}],[14.638787,{"InductiveProof":{"prop_name":"take x (take x xs) == take x xs","lemmas":[]}}],[14.723564,{"PlainProof":{"prop_name":"take (S x) (y:xs) == y:take x xs","lemmas":[]}}],[17.749923,{"InductiveProof":{"prop_name":"take (S x) (take x xs) == take x xs","lemmas":[]}}],[17.762013,{"Discard":{"discarded":["map f [] == []","map f [] == []","take x [] == []","take x [] == []","take x [] == []","take Z xs == []","take Z xs == []","take Z xs == []","map S [] == []","take Z [] == []","take x (map f xs) == map f (take x xs)","take x (map f xs) == map f (take x xs)","take x (map f xs) == map f (take x xs)","take x (map f xs) == map f (take x xs)","take x (map f xs) == map f (take x xs)","take x (map f xs) == map f (take x xs)","take x (map f xs) == map f (take x xs)","take x (map f xs) == map f (take x xs)","take x (map f xs) == map f (take x xs)","take x (map f xs) == map f (take x xs)","take x (map f xs) == map f (take x xs)","take x (map f xs) == map f (take x xs)","take x (take y xs) == take y (take x xs)","take x (take y xs) == take y (take x xs)","take x (take y xs) == take y (take x xs)","take x (map f xs) == map f (take x xs)","take x (map f xs) == map f (take x xs)","take x (map f xs) == map f (take x xs)","take x (map f xs) == map f (take x xs)","take x (map f xs) == map f (take x xs)","take x (map f xs) == map f (take x xs)","take x (take y xs) == take y (take x xs)","take x (take y xs) == take y (take x xs)","take x (take y xs) == take y (take x xs)","take x (take y xs) == take y (take x xs)","take x (take y xs) == take y (take x xs)","take x (take y xs) == take y (take x xs)","take x (take x xs) == take x xs","take x (take x xs) == take x xs","take x (take x xs) == take x xs","take x (take x xs) == take x xs","take x (take x xs) == take x xs","take x (take x xs) == take x xs","take x (take x xs) == take x xs","take x (take x xs) == take x xs","take x (take x xs) == take x xs","take (S x) (y:xs) == y:take x xs","take (S x) (y:xs) == y:take x xs","take (S x) (y:xs) == y:take x xs","take (S x) (y:xs) == y:take x xs","take (S x) (y:xs) == y:take x xs","take (S x) (y:xs) == y:take x xs","take (S x) (y:xs) == y:take x xs","take (S x) (y:xs) == y:take x xs","take (S x) (y:xs) == y:take x xs","take (S x) (y:xs) == y:take x xs","take (S x) (y:xs) == y:take x xs","take (S x) (y:xs) == y:take x xs","take (S x) (y:xs) == y:take x xs","take (S x) (y:xs) == y:take x xs","take (S x) (y:xs) == y:take x xs","take (S x) (y:xs) == y:take x xs","take (S x) (y:xs) == y:take x xs","take (S x) (y:xs) == y:take x xs","map S (take x xs) == take x (map S xs)","map S (take x xs) == take x (map S xs)","map S (take x xs) == take x (map S xs)","map S (take x xs) == take x (map S xs)","map S (take x xs) == take x (map S xs)","map S (take x xs) == take x (map S xs)","map S (take x xs) == take x (map S xs)","map S (take x xs) == take x (map S xs)","map S (take x xs) == take x (map S xs)","take Z (map f xs) == []","take Z (map f xs) == []","take Z (map f xs) == []","take Z (map f xs) == []","take Z (map f xs) == []","take Z (map f xs) == []","take Z (x:xs) == []","take Z (x:xs) == []","take Z (x:xs) == []","take Z (x:xs) == []","take Z (x:xs) == []","take Z (x:xs) == []","take Z (x:xs) == []","take Z (x:xs) == []","take Z (x:xs) == []","take Z (take x xs) == []","take Z (take x xs) == []","take Z (take x xs) == []","take Z (take x xs) == []","take Z (take x xs) == []","take Z (take x xs) == []","take Z (take x xs) == []","take Z (take x xs) == []","take Z (take x xs) == []","take (S x) (x:xs) == x:take x xs","take (S x) (x:xs) == x:take x xs","take (S x) (x:xs) == x:take x xs","take (S x) (take x xs) == take x xs","take (S x) (take x xs) == take x xs","take (S x) (take x xs) == take x xs","take (S x) (x:xs) == x:take x xs","take (S x) (x:xs) == x:take x xs","take (S x) (x:xs) == x:take x xs","take (S x) (take x xs) == take x xs","take (S x) (take x xs) == take x xs","take (S x) (take x xs) == take x xs","take (S x) (x:xs) == x:take x xs","take (S x) (x:xs) == x:take x xs","take (S x) (x:xs) == x:take x xs","take (S x) (take x xs) == take x xs","take (S x) (take x xs) == take x xs","take (S x) (take x xs) == take x xs","take (S x) [] == []","take (S x) [] == []","take (S x) [] == []","S x:map S xs == map S (x:xs)","S x:map S xs == map S (x:xs)","S x:map S xs == map S (x:xs)","S x:map S xs == map S (x:xs)","S x:map S xs == map S (x:xs)","S x:map S xs == map S (x:xs)","S x:map S xs == map S (x:xs)","S x:map S xs == map S (x:xs)","S x:map S xs == map S (x:xs)","take (S x) (y:[]) == y:[]","take (S x) (y:[]) == y:[]","take (S x) (Z:xs) == Z:take x xs","take (S x) (Z:xs) == Z:take x xs","take (S x) (Z:xs) == Z:take x xs","take (S x) (y:[]) == y:[]","take (S x) (y:[]) == y:[]","take (S x) (Z:xs) == Z:take x xs","take (S x) (Z:xs) == Z:take x xs","take (S x) (Z:xs) == Z:take x xs","take (S x) (y:[]) == y:[]","take (S x) (y:[]) == y:[]","take (S x) (Z:xs) == Z:take x xs","take (S x) (Z:xs) == Z:take x xs","take (S x) (Z:xs) == Z:take x xs","take (S Z) (x:xs) == x:[]","take (S Z) (x:xs) == x:[]","take (S Z) (x:xs) == x:[]","take (S Z) (x:xs) == x:[]","take (S Z) (x:xs) == x:[]","take (S Z) (x:xs) == x:[]","take (S Z) (x:xs) == x:[]","take (S Z) (x:xs) == x:[]","take (S Z) (x:xs) == x:[]"]}}],[20.833012,{"FailedProof":{"prop_name":"S x:map S xs == map S (x:xs)"}}],[22.860409,{"FailedProof":{"prop_name":"map S (x:[]) == S x:[]"}}],[22.860448,{"Discard":{"discarded":["map S (x:[]) == S x:[]","map S (x:[]) == S x:[]","take Z (x:[]) == []","take Z (x:[]) == []","take Z (x:[]) == []","take Z (map S xs) == []","take Z (map S xs) == []","take Z (map S xs) == []","take Z (Z:xs) == []","take Z (Z:xs) == []","take Z (Z:xs) == []","take (S x) (x:[]) == x:[]","take (S x) (x:[]) == x:[]","take (S x) (x:[]) == x:[]","take (S Z) [] == []","take (S x) (Z:[]) == Z:[]","take (S x) (Z:[]) == Z:[]","take (S x) (Z:[]) == Z:[]","S Z:map S xs == map S (Z:xs)","S Z:map S xs == map S (Z:xs)","take (S Z) (x:[]) == x:[]","take (S Z) (x:[]) == x:[]","take (S Z) (x:[]) == x:[]","take (S Z) (Z:xs) == Z:[]","take (S Z) (Z:xs) == Z:[]","take (S Z) (Z:xs) == Z:[]"]}}],[24.879568,{"FailedProof":{"prop_name":"S Z:map S xs == map S (Z:xs)"}}],[24.879585,{"FailedProof":{"prop_name":"map S (Z:[]) == S Z:[]"}}],[24.879619,{"Discard":{"discarded":["take Z (Z:[]) == []","take (S Z) (Z:[]) == Z:[]"]}}],[30.965969,{"FailedProof":{"prop_name":"take y (take x xs) == take x (take y xs)"}}],[33.985083,{"FailedProof":{"prop_name":"S x:map S xs == map S (x:xs)"}}],[36.009603,{"FailedProof":{"prop_name":"map S (x:[]) == S x:[]"}}],[37.011468,{"FailedProof":{"prop_name":"S Z:map S xs == map S (Z:xs)"}}],[38.016436,{"FailedProof":{"prop_name":"map S (Z:[]) == S Z:[]"}}],[38.016455,{"StartingUserLemmas":[]}],[38.087088,{"PlainProof":{"prop_name":"prop_41","lemmas":[]}}],[38.087106,{"Finished":{"qs_proved":["take x (map f xs) == map f (take x xs)","take x (take x xs) == take x xs","take (S x) (take x xs) == take x xs"],"unproved":[],"proved":["prop_41"],"qs_unproved":["take x (take y xs) == take y (take x xs)","S x:map S xs == map S (x:xs)","map S (x:[]) == S x:[]","S Z:map S xs == map S (Z:xs)","map S (Z:[]) == S Z:[]"]}}]]