[[2.0e-6,{"Started":[]}],[1.87519,{"FileProcessed":[]}],[2.555175,{"QuickSpecDone":{"eqs":894,"classes":988}}],[3.915706,{"InductiveProof":{"lemmas":[],"prop_name":"y==x == x==y"}}],[4.945268,{"FailedProof":{"prop_name":"subset xs xs == True"}}],[5.981001,{"FailedProof":{"prop_name":"intersect xs xs == xs"}}],[6.950721,{"InductiveProof":{"lemmas":[],"prop_name":"x==x == True"}}],[7.955126,{"InductiveProof":{"lemmas":[],"prop_name":"intersect xs [] == []"}}],[11.094033,{"FailedProof":{"prop_name":"subset xs (intersect zs ys) == subset xs (intersect ys zs)"}}],[15.250037,{"FailedProof":{"prop_name":"intersect xs (intersect zs ys) == intersect xs (intersect ys zs)"}}],[18.3655,{"FailedProof":{"prop_name":"elem x (intersect ys xs) == elem x (intersect xs ys)"}}],[22.491605,{"FailedProof":{"prop_name":"subset (intersect ys xs) zs == subset (intersect xs ys) zs"}}],[25.754809,{"FailedProof":{"prop_name":"intersect (intersect xs ys) zs == intersect xs (intersect ys zs)"}}],[27.857164,{"FailedProof":{"prop_name":"subset xs (intersect xs ys) == subset xs ys"}}],[29.911668,{"FailedProof":{"prop_name":"subset xs (x:xs) == True"}}],[31.967045,{"FailedProof":{"prop_name":"intersect xs (x:xs) == xs"}}],[31.991326,{"PlainProof":{"lemmas":[],"prop_name":"elem x (x:xs) == True"}}],[34.048283,{"FailedProof":{"prop_name":"subset (x:xs) xs == elem x xs"}}],[35.00249,{"InductiveProof":{"lemmas":[],"prop_name":"x==S x == False"}}],[35.060252,{"PlainProof":{"lemmas":[],"prop_name":"subset (x:xs) (x:ys) == subset xs (x:ys)"}}],[39.116372,{"FailedProof":{"prop_name":"subset (x:xs) (y:xs) == elem x (y:xs)"}}],[42.276589,{"PlainProof":{"lemmas":[],"prop_name":"elem x (y:[]) == x==y"}}],[43.257352,{"FailedProof":{"prop_name":"intersect (intersect xs ys) (x:xs) == intersect xs ys"}}],[43.309025,{"PlainProof":{"lemmas":[],"prop_name":"subset (x:xs) [] == False"}}],[43.330268,{"PlainProof":{"lemmas":[],"prop_name":"elem (S x) (x:xs) == elem (S x) xs"}}],[43.386719,{"PlainProof":{"lemmas":[],"prop_name":"subset (x:[]) xs == elem x xs"}}],[47.425047,{"FailedProof":{"prop_name":"subset (y:xs) (x:[]) == subset (x:xs) (y:[])"}}],[47.486342,{"PlainProof":{"lemmas":[],"prop_name":"elem (S x) (Z:xs) == elem (S x) xs"}}],[47.528362,{"PlainProof":{"lemmas":[],"prop_name":"intersect (x:[]) (x:xs) == x:[]"}}],[49.570847,{"InductiveProof":{"lemmas":[],"prop_name":"intersect (y:[]) (x:[]) == intersect (x:[]) (y:[])"}}],[52.789404,{"FailedProof":{"prop_name":"intersect (intersect xs zs) ys == intersect xs (intersect ys zs)"}}],[54.901463,{"FailedProof":{"prop_name":"subset xs (intersect ys xs) == subset xs ys"}}],[57.001962,{"FailedProof":{"prop_name":"intersect xs (intersect xs ys) == intersect xs ys"}}],[59.106976,{"FailedProof":{"prop_name":"intersect xs (intersect ys xs) == intersect xs ys"}}],[61.208436,{"FailedProof":{"prop_name":"subset (intersect xs ys) xs == True"}}],[62.287231,{"InductiveProof":{"lemmas":[],"prop_name":"subset (intersect xs ys) ys == True"}}],[64.389884,{"FailedProof":{"prop_name":"intersect (intersect xs ys) xs == intersect xs ys"}}],[65.46191,{"InductiveProof":{"lemmas":[],"prop_name":"intersect (intersect xs ys) ys == intersect xs ys"}}],[70.833701,{"InductiveProof":{"lemmas":[],"prop_name":"subset (intersect ys xs) (x:zs) == subset (intersect xs ys) (x:zs)"}}],[77.027217,{"FailedProof":{"prop_name":"subset (x:xs) (intersect zs ys) == subset (x:xs) (intersect ys zs)"}}],[85.469167,{"FailedProof":{"prop_name":"subset (y:xs) (intersect ys zs) == subset (x:xs) (intersect ys zs)"}}],[93.868813,{"FailedProof":{"prop_name":"subset (y:xs) (intersect zs ys) == subset (x:xs) (intersect ys zs)"}}],[99.928031,{"FailedProof":{"prop_name":"intersect (x:xs) (intersect zs ys) == intersect (x:xs) (intersect ys zs)"}}],[104.072888,{"FailedProof":{"prop_name":"subset (intersect xs ys) (intersect xs zs) == subset (intersect xs ys) zs"}}],[107.259529,{"FailedProof":{"prop_name":"subset (intersect xs ys) (intersect ys zs) == subset (intersect xs ys) zs"}}],[111.40157,{"FailedProof":{"prop_name":"subset (intersect xs ys) (intersect zs xs) == subset (intersect xs ys) zs"}}],[114.597623,{"FailedProof":{"prop_name":"subset (intersect xs ys) (intersect zs ys) == subset (intersect xs ys) zs"}}],[115.68174,{"InductiveProof":{"lemmas":[],"prop_name":"subset (intersect xs ys) (x:xs) == True"}}],[117.994564,{"InductiveProof":{"lemmas":[],"prop_name":"subset (intersect xs ys) (x:ys) == True"}}],[122.138815,{"FailedProof":{"prop_name":"subset (intersect ys xs) (intersect xs zs) == subset (intersect xs ys) zs"}}],[125.271994,{"FailedProof":{"prop_name":"subset (intersect ys xs) (intersect ys zs) == subset (intersect xs ys) zs"}}],[129.42399,{"FailedProof":{"prop_name":"subset (intersect ys xs) (intersect zs xs) == subset (intersect xs ys) zs"}}],[132.558468,{"FailedProof":{"prop_name":"subset (intersect ys xs) (intersect zs ys) == subset (intersect xs ys) zs"}}],[136.628822,{"FailedProof":{"prop_name":"subset (x:xs) (intersect ys xs) == subset (x:xs) (intersect xs ys)"}}],[139.746008,{"FailedProof":{"prop_name":"subset (x:ys) (intersect ys xs) == subset (x:ys) (intersect xs ys)"}}],[143.889644,{"FailedProof":{"prop_name":"intersect (intersect xs ys) (intersect xs zs) == intersect xs (intersect ys zs)"}}],[147.116635,{"FailedProof":{"prop_name":"intersect (intersect xs ys) (intersect ys zs) == intersect xs (intersect ys zs)"}}],[151.345916,{"FailedProof":{"prop_name":"intersect (intersect xs ys) (intersect zs xs) == intersect xs (intersect ys zs)"}}],[154.54818,{"FailedProof":{"prop_name":"intersect (intersect xs ys) (intersect zs ys) == intersect xs (intersect ys zs)"}}],[156.697573,{"InductiveProof":{"lemmas":[],"prop_name":"intersect (intersect xs ys) (x:ys) == intersect xs ys"}}],[160.964991,{"FailedProof":{"prop_name":"intersect (intersect xs zs) (intersect xs ys) == intersect xs (intersect ys zs)"}}],[165.185356,{"FailedProof":{"prop_name":"intersect (intersect xs zs) (intersect ys xs) == intersect xs (intersect ys zs)"}}],[168.486003,{"FailedProof":{"prop_name":"intersect (intersect xs zs) (intersect ys zs) == intersect xs (intersect ys zs)"}}],[172.708174,{"FailedProof":{"prop_name":"intersect (intersect xs zs) (intersect zs ys) == intersect xs (intersect ys zs)"}}],[175.847206,{"FailedProof":{"prop_name":"intersect (x:xs) (intersect ys xs) == intersect (x:xs) (intersect xs ys)"}}],[179.95166,{"FailedProof":{"prop_name":"intersect (x:ys) (intersect ys xs) == intersect (x:ys) (intersect xs ys)"}}],[183.108922,{"FailedProof":{"prop_name":"elem (S x) (intersect ys xs) == elem (S x) (intersect xs ys)"}}],[185.229248,{"FailedProof":{"prop_name":"elem Z (intersect ys xs) == elem Z (intersect xs ys)"}}],[186.324324,{"InductiveProof":{"lemmas":[],"prop_name":"subset (intersect xs ys) (intersect xs ys) == True"}}],[188.447458,{"FailedProof":{"prop_name":"subset (intersect xs ys) (intersect ys xs) == True"}}],[190.552837,{"InductiveProof":{"lemmas":[],"prop_name":"subset (intersect ys xs) [] == subset (intersect xs ys) []"}}],[192.661009,{"FailedProof":{"prop_name":"subset (x:xs) (x:xs) == True"}}],[193.697312,{"InductiveProof":{"lemmas":[],"prop_name":"intersect (intersect xs ys) (intersect xs ys) == intersect xs ys"}}],[195.832718,{"FailedProof":{"prop_name":"intersect (intersect xs ys) (intersect ys xs) == intersect xs ys"}}],[196.766831,{"InductiveProof":{"lemmas":[],"prop_name":"intersect (x:xs) (x:xs) == x:xs"}}],[196.801898,{"PlainProof":{"lemmas":[],"prop_name":"subset xs (Z:xs) == True"}}],[196.827139,{"PlainProof":{"lemmas":[],"prop_name":"intersect xs (Z:xs) == xs"}}],[196.907133,{"PlainProof":{"lemmas":[],"prop_name":"subset (Z:xs) xs == elem Z xs"}}],[199.555086,{"InductiveProof":{"lemmas":[],"prop_name":"subset (x:[]) (intersect ys xs) == elem x (intersect xs ys)"}}],[205.69722,{"FailedProof":{"prop_name":"subset (Z:xs) (intersect ys zs) == subset (x:xs) (intersect ys zs)"}}],[210.945672,{"FailedProof":{"prop_name":"subset (Z:xs) (intersect zs ys) == subset (x:xs) (intersect ys zs)"}}],[213.087069,{"InductiveProof":{"lemmas":[],"prop_name":"subset (Z:ys) (intersect zs xs) == subset (Z:ys) (intersect xs zs)"}}],[213.12751,{"PlainProof":{"lemmas":[],"prop_name":"intersect (x:[]) (intersect ys xs) == intersect (x:[]) (intersect xs ys)"}}],[215.609776,{"PlainProof":{"lemmas":[],"prop_name":"subset (x:xs) (Z:xs) == elem x (Z:xs)"}}],[215.983349,{"InductiveProof":{"lemmas":[],"prop_name":"intersect (Z:xs) (intersect zs ys) == intersect (Z:xs) (intersect ys zs)"}}],[218.100056,{"PlainProof":{"lemmas":[],"prop_name":"subset (Z:xs) (x:xs) == elem Z (x:xs)"}}],[218.107598,{"FailedProof":{"prop_name":"intersect (intersect xs ys) (Z:xs) == intersect xs ys"}}],[218.17679,{"PlainProof":{"lemmas":[],"prop_name":"subset (Z:xs) (x:[]) == subset (x:xs) (Z:[])"}}],[220.30498,{"InductiveProof":{"lemmas":[],"prop_name":"subset xs (intersect zs ys) == subset xs (intersect ys zs)"}}],[222.40608,{"InductiveProof":{"lemmas":[],"prop_name":"intersect xs (intersect zs ys) == intersect xs (intersect ys zs)"}}],[223.457678,{"InductiveProof":{"lemmas":[],"prop_name":"subset (intersect ys xs) zs == subset (intersect xs ys) zs"}}],[226.68086,{"FailedProof":{"prop_name":"intersect (intersect xs ys) zs == intersect xs (intersect ys zs)"}}],[228.802815,{"PlainProof":{"lemmas":[],"prop_name":"subset (x:xs) xs == elem x xs"}}],[228.81023,{"FailedProof":{"prop_name":"subset xs (intersect xs ys) == subset xs ys"}}],[229.02377,{"PlainProof":{"lemmas":[],"prop_name":"subset (x:xs) (y:xs) == elem x (y:xs)"}}],[233.067881,{"FailedProof":{"prop_name":"intersect (intersect xs ys) (x:xs) == intersect xs ys"}}],[233.270194,{"PlainProof":{"lemmas":[],"prop_name":"subset (y:xs) (x:[]) == subset (x:xs) (y:[])"}}],[237.388644,{"FailedProof":{"prop_name":"intersect (intersect xs zs) ys == intersect xs (intersect ys zs)"}}],[239.509413,{"FailedProof":{"prop_name":"subset xs (intersect ys xs) == subset xs ys"}}],[241.635857,{"FailedProof":{"prop_name":"intersect xs (intersect xs ys) == intersect xs ys"}}],[243.773894,{"FailedProof":{"prop_name":"intersect xs (intersect ys xs) == intersect xs ys"}}],[244.8176,{"InductiveProof":{"lemmas":[],"prop_name":"intersect (intersect xs ys) xs == intersect xs ys"}}],[253.354362,{"FailedProof":{"prop_name":"subset (y:xs) (intersect ys zs) == subset (x:xs) (intersect ys zs)"}}],[261.891906,{"FailedProof":{"prop_name":"subset (y:xs) (intersect zs ys) == subset (x:xs) (intersect ys zs)"}}],[266.085182,{"FailedProof":{"prop_name":"subset (intersect xs ys) (intersect xs zs) == subset (intersect xs ys) zs"}}],[269.303687,{"FailedProof":{"prop_name":"subset (intersect xs ys) (intersect ys zs) == subset (intersect xs ys) zs"}}],[273.481151,{"FailedProof":{"prop_name":"subset (intersect xs ys) (intersect zs xs) == subset (intersect xs ys) zs"}}],[276.70415,{"FailedProof":{"prop_name":"subset (intersect xs ys) (intersect zs ys) == subset (intersect xs ys) zs"}}],[280.876725,{"FailedProof":{"prop_name":"subset (intersect ys xs) (intersect xs zs) == subset (intersect xs ys) zs"}}],[284.100968,{"FailedProof":{"prop_name":"subset (intersect ys xs) (intersect ys zs) == subset (intersect xs ys) zs"}}],[288.282697,{"FailedProof":{"prop_name":"subset (intersect ys xs) (intersect zs xs) == subset (intersect xs ys) zs"}}],[291.503244,{"FailedProof":{"prop_name":"subset (intersect ys xs) (intersect zs ys) == subset (intersect xs ys) zs"}}],[295.69058,{"FailedProof":{"prop_name":"intersect (intersect xs ys) (intersect xs zs) == intersect xs (intersect ys zs)"}}],[298.91362,{"FailedProof":{"prop_name":"intersect (intersect xs ys) (intersect ys zs) == intersect xs (intersect ys zs)"}}],[303.131354,{"FailedProof":{"prop_name":"intersect (intersect xs ys) (intersect zs xs) == intersect xs (intersect ys zs)"}}],[306.356807,{"FailedProof":{"prop_name":"intersect (intersect xs ys) (intersect zs ys) == intersect xs (intersect ys zs)"}}],[310.550914,{"FailedProof":{"prop_name":"intersect (intersect xs zs) (intersect xs ys) == intersect xs (intersect ys zs)"}}],[313.778549,{"FailedProof":{"prop_name":"intersect (intersect xs zs) (intersect ys xs) == intersect xs (intersect ys zs)"}}],[317.960195,{"FailedProof":{"prop_name":"intersect (intersect xs zs) (intersect ys zs) == intersect xs (intersect ys zs)"}}],[321.179775,{"FailedProof":{"prop_name":"intersect (intersect xs zs) (intersect zs ys) == intersect xs (intersect ys zs)"}}],[327.417836,{"FailedProof":{"prop_name":"subset (Z:xs) (intersect ys zs) == subset (x:xs) (intersect ys zs)"}}],[332.710901,{"FailedProof":{"prop_name":"subset (Z:xs) (intersect zs ys) == subset (x:xs) (intersect ys zs)"}}],[333.227961,{"PlainProof":{"lemmas":[],"prop_name":"intersect (intersect xs ys) (Z:xs) == intersect xs ys"}}],[337.417553,{"FailedProof":{"prop_name":"intersect (intersect xs ys) zs == intersect xs (intersect ys zs)"}}],[339.551289,{"FailedProof":{"prop_name":"subset xs (intersect xs ys) == subset xs ys"}}],[343.73485,{"FailedProof":{"prop_name":"intersect (intersect xs zs) ys == intersect xs (intersect ys zs)"}}],[345.858268,{"FailedProof":{"prop_name":"subset xs (intersect ys xs) == subset xs ys"}}],[347.989627,{"InductiveProof":{"lemmas":[],"prop_name":"intersect xs (intersect xs ys) == intersect xs ys"}}],[350.117203,{"FailedProof":{"prop_name":"intersect xs (intersect ys xs) == intersect xs ys"}}],[358.645707,{"FailedProof":{"prop_name":"subset (y:xs) (intersect ys zs) == subset (x:xs) (intersect ys zs)"}}],[367.174651,{"FailedProof":{"prop_name":"subset (y:xs) (intersect zs ys) == subset (x:xs) (intersect ys zs)"}}],[371.349988,{"FailedProof":{"prop_name":"subset (intersect xs ys) (intersect xs zs) == subset (intersect xs ys) zs"}}],[374.566381,{"FailedProof":{"prop_name":"subset (intersect xs ys) (intersect ys zs) == subset (intersect xs ys) zs"}}],[378.776876,{"FailedProof":{"prop_name":"subset (intersect xs ys) (intersect zs xs) == subset (intersect xs ys) zs"}}],[381.993682,{"FailedProof":{"prop_name":"subset (intersect xs ys) (intersect zs ys) == subset (intersect xs ys) zs"}}],[386.173694,{"FailedProof":{"prop_name":"subset (intersect ys xs) (intersect xs zs) == subset (intersect xs ys) zs"}}],[389.393023,{"FailedProof":{"prop_name":"subset (intersect ys xs) (intersect ys zs) == subset (intersect xs ys) zs"}}],[393.059342,{"InductiveProof":{"lemmas":[],"prop_name":"subset (intersect ys xs) (intersect zs xs) == subset (intersect xs ys) zs"}}],[396.455117,{"InductiveProof":{"lemmas":[],"prop_name":"subset (intersect ys xs) (intersect zs ys) == subset (intersect xs ys) zs"}}],[400.701462,{"FailedProof":{"prop_name":"intersect (intersect xs ys) (intersect xs zs) == intersect xs (intersect ys zs)"}}],[403.924337,{"FailedProof":{"prop_name":"intersect (intersect xs ys) (intersect ys zs) == intersect xs (intersect ys zs)"}}],[408.121247,{"FailedProof":{"prop_name":"intersect (intersect xs ys) (intersect zs xs) == intersect xs (intersect ys zs)"}}],[411.351771,{"FailedProof":{"prop_name":"intersect (intersect xs ys) (intersect zs ys) == intersect xs (intersect ys zs)"}}],[415.543488,{"FailedProof":{"prop_name":"intersect (intersect xs zs) (intersect xs ys) == intersect xs (intersect ys zs)"}}],[418.775238,{"FailedProof":{"prop_name":"intersect (intersect xs zs) (intersect ys xs) == intersect xs (intersect ys zs)"}}],[423.041036,{"FailedProof":{"prop_name":"intersect (intersect xs zs) (intersect ys zs) == intersect xs (intersect ys zs)"}}],[426.253104,{"FailedProof":{"prop_name":"intersect (intersect xs zs) (intersect zs ys) == intersect xs (intersect ys zs)"}}],[432.5194,{"FailedProof":{"prop_name":"subset (Z:xs) (intersect ys zs) == subset (x:xs) (intersect ys zs)"}}],[437.790205,{"FailedProof":{"prop_name":"subset (Z:xs) (intersect zs ys) == subset (x:xs) (intersect ys zs)"}}],[442.018844,{"FailedProof":{"prop_name":"intersect (intersect xs ys) zs == intersect xs (intersect ys zs)"}}],[445.245959,{"FailedProof":{"prop_name":"intersect (intersect xs zs) ys == intersect xs (intersect ys zs)"}}],[453.759471,{"FailedProof":{"prop_name":"subset (y:xs) (intersect ys zs) == subset (x:xs) (intersect ys zs)"}}],[462.284637,{"FailedProof":{"prop_name":"subset (y:xs) (intersect zs ys) == subset (x:xs) (intersect ys zs)"}}],[466.517327,{"FailedProof":{"prop_name":"intersect (intersect xs ys) (intersect xs zs) == intersect xs (intersect ys zs)"}}],[469.741459,{"FailedProof":{"prop_name":"intersect (intersect xs ys) (intersect ys zs) == intersect xs (intersect ys zs)"}}],[474.01445,{"FailedProof":{"prop_name":"intersect (intersect xs ys) (intersect zs xs) == intersect xs (intersect ys zs)"}}],[477.220327,{"FailedProof":{"prop_name":"intersect (intersect xs ys) (intersect zs ys) == intersect xs (intersect ys zs)"}}],[481.479414,{"FailedProof":{"prop_name":"intersect (intersect xs zs) (intersect xs ys) == intersect xs (intersect ys zs)"}}],[484.708884,{"FailedProof":{"prop_name":"intersect (intersect xs zs) (intersect ys xs) == intersect xs (intersect ys zs)"}}],[488.903199,{"FailedProof":{"prop_name":"intersect (intersect xs zs) (intersect ys zs) == intersect xs (intersect ys zs)"}}],[492.123291,{"FailedProof":{"prop_name":"intersect (intersect xs zs) (intersect zs ys) == intersect xs (intersect ys zs)"}}],[498.387898,{"FailedProof":{"prop_name":"subset (Z:xs) (intersect ys zs) == subset (x:xs) (intersect ys zs)"}}],[503.675454,{"FailedProof":{"prop_name":"subset (Z:xs) (intersect zs ys) == subset (x:xs) (intersect ys zs)"}}],[503.675491,{"StartingUserLemmas":[]}],[504.748675,{"InductiveProof":{"lemmas":[],"prop_name":"prop_T41"}}],[504.748815,{"Finished":{"qs_proved":["y==x == x==y","x==x == True","intersect xs [] == []","x==S x == False","intersect (y:[]) (x:[]) == intersect (x:[]) (y:[])","subset (intersect xs ys) ys == True","intersect (intersect xs ys) ys == intersect xs ys","subset (intersect ys xs) (x:zs) == subset (intersect xs ys) (x:zs)","subset (intersect xs ys) (x:xs) == True","subset (intersect xs ys) (x:ys) == True","intersect (intersect xs ys) (x:ys) == intersect xs ys","subset (intersect xs ys) (intersect xs ys) == True","subset (intersect ys xs) [] == subset (intersect xs ys) []","intersect (intersect xs ys) (intersect xs ys) == intersect xs ys","intersect (x:xs) (x:xs) == x:xs","subset (x:[]) (intersect ys xs) == elem x (intersect xs ys)","subset (Z:ys) (intersect zs xs) == subset (Z:ys) (intersect xs zs)","intersect (Z:xs) (intersect zs ys) == intersect (Z:xs) (intersect ys zs)","subset xs (intersect zs ys) == subset xs (intersect ys zs)","intersect xs (intersect zs ys) == intersect xs (intersect ys zs)","subset (intersect ys xs) zs == subset (intersect xs ys) zs","intersect (intersect xs ys) xs == intersect xs ys","intersect xs (intersect xs ys) == intersect xs ys","subset (intersect ys xs) (intersect zs xs) == subset (intersect xs ys) zs","subset (intersect ys xs) (intersect zs ys) == subset (intersect xs ys) zs"],"proved":["prop_T41"],"qs_unproved":["intersect (intersect xs ys) zs == intersect xs (intersect ys zs)","intersect (intersect xs ys) zs == intersect xs (intersect zs ys)","subset (x:xs) (intersect ys zs) == subset (y:xs) (intersect ys zs)","subset (x:xs) (intersect ys zs) == subset (y:xs) (intersect zs ys)","intersect (intersect xs ys) (intersect xs zs) == intersect xs (intersect ys zs)","intersect (intersect xs ys) (intersect ys zs) == intersect xs (intersect ys zs)","intersect (intersect xs ys) (intersect zs xs) == intersect xs (intersect ys zs)","intersect (intersect xs ys) (intersect zs ys) == intersect xs (intersect ys zs)","intersect (intersect xs ys) (intersect xs zs) == intersect xs (intersect zs ys)","intersect (intersect xs ys) (intersect zs xs) == intersect xs (intersect zs ys)","intersect (intersect xs ys) (intersect zs ys) == intersect xs (intersect zs ys)","intersect (intersect xs ys) (intersect ys zs) == intersect xs (intersect zs ys)","subset (Z:xs) (intersect ys zs) == subset (x:xs) (intersect ys zs)","subset (Z:xs) (intersect ys zs) == subset (x:xs) (intersect zs ys)"],"unproved":[]}}]]