[[2.0e-6,{"Started":[]}],[5.262416,{"FileProcessed":[]}],[6.405985,{"QuickSpecDone":{"classes":2765,"eqs":1001}}],[9.192135,{"FailedProof":{"prop_name":"y+x == x+y"}}],[9.203392,{"InductiveProof":{"lemmas":[],"prop_name":"xs++[] == xs"}}],[9.236218,{"PlainProof":{"lemmas":[],"prop_name":"elem y [] == elem x []"}}],[9.242309,{"PlainProof":{"lemmas":[],"prop_name":"drop x [] == []"}}],[9.274258,{"PlainProof":{"lemmas":[],"prop_name":"[]++xs == xs"}}],[10.247598,{"InductiveProof":{"lemmas":[],"prop_name":"x+Z == x"}}],[10.274149,{"PlainProof":{"lemmas":[],"prop_name":"drop Z xs == xs"}}],[10.279359,{"PlainProof":{"lemmas":[],"prop_name":"length [] == Z"}}],[12.308116,{"FailedProof":{"prop_name":"elem x (ys++xs) == elem x (xs++ys)"}}],[14.320516,{"FailedProof":{"prop_name":"drop y (drop x xs) == drop x (drop y xs)"}}],[16.339157,{"FailedProof":{"prop_name":"y+(x+z) == x+(y+z)"}}],[18.346444,{"InductiveProof":{"lemmas":[],"prop_name":"(xs++ys)++zs == xs++(ys++zs)"}}],[18.381001,{"PlainProof":{"lemmas":[],"prop_name":"(x:xs)++ys == x:(xs++ys)"}}],[20.399145,{"FailedProof":{"prop_name":"drop (x+y) xs == drop x (drop y xs)"}}],[21.440965,{"PlainProof":{"lemmas":[],"prop_name":"length (y:xs) == length (x:xs)"}}],[22.429895,{"FailedProof":{"prop_name":"length (ys++xs) == length (xs++ys)"}}],[24.442647,{"FailedProof":{"prop_name":"elem x (x:ys) == elem x (x:xs)"}}],[26.450039,{"FailedProof":{"prop_name":"elem x (xs++xs) == elem x xs"}}],[28.488031,{"FailedProof":{"prop_name":"elem y (y:xs) == elem x (x:xs)"}}],[29.49132,{"InductiveProof":{"lemmas":[],"prop_name":"x+S y == S (x+y)"}}],[29.50974,{"PlainProof":{"lemmas":[],"prop_name":"S (length xs) == length (x:xs)"}}],[30.512314,{"InductiveProof":{"lemmas":[],"prop_name":"drop (length xs) xs == []"}}],[31.007956,{"PlainProof":{"lemmas":[],"prop_name":"drop (S x) (y:xs) == drop x xs"}}],[31.556557,{"PlainProof":{"lemmas":[],"prop_name":"drop (x+y) (y:xs) == drop (x+y) (x:xs)"}}],[33.580496,{"FailedProof":{"prop_name":"elem y (x:[]) == elem x (y:[])"}}],[34.587904,{"FailedProof":{"prop_name":"elem (S x) (x:xs) == elem (S x) xs"}}],[35.618515,{"InductiveProof":{"lemmas":[],"prop_name":"drop (length xs) (xs++ys) == ys"}}],[36.64649,{"InductiveProof":{"lemmas":[],"prop_name":"length xs+length ys == length (xs++ys)"}}],[38.70398,{"FailedProof":{"prop_name":"elem (x+z) (z:[]) == elem (x+y) (y:[])"}}],[39.726189,{"PlainProof":{"lemmas":[],"prop_name":"elem (S x) (Z:xs) == elem (S x) xs"}}],[41.024432,{"PlainProof":{"lemmas":[],"prop_name":"drop (x+x) (y:[]) == drop x (y:[])"}}],[41.824306,{"FailedProof":{"prop_name":"elem (x+x) (Z:xs) == elem (x+x) (x:xs)"}}],[41.849744,{"Discard":{"discarded":["xs++[] == xs","[]++xs == xs","drop Z xs == xs","drop (length xs) (xs++ys) == ys","drop (length xs) (xs++ys) == ys","drop (length xs) (xs++xs) == xs","drop (S Z) (x:xs) == xs","drop (S Z) (x:xs) == xs","drop (S Z) (x:xs) == xs","drop (S Z) (Z:xs) == xs","xs++[] == xs","[]++xs == xs","drop Z xs == xs","drop (length xs) (xs++ys) == ys","drop (length xs) (xs++ys) == ys","drop (length xs) (xs++xs) == xs","drop (S Z) (x:xs) == xs","drop (S Z) (x:xs) == xs","drop (S Z) (x:xs) == xs","drop (S Z) (Z:xs) == xs","xs++[] == xs","[]++xs == xs","drop Z xs == xs","drop (length xs) (xs++ys) == ys","drop (length xs) (xs++ys) == ys","drop (length xs) (xs++xs) == xs","drop (S Z) (x:xs) == xs","drop (S Z) (x:xs) == xs","drop (S Z) (x:xs) == xs","drop (S Z) (Z:xs) == xs","x+Z == x","x+Z == x","Z+x == x","x+Z == x","Z+x == x","drop x [] == []","drop x [] == []","drop x [] == []","[]++[] == []","drop Z [] == []","drop (length xs) xs == []","drop (length xs) xs == []","drop (length xs) xs == []","drop (x+y) [] == []","drop (x+y) [] == []","drop (x+y) [] == []"]}}],[41.86715,{"PlainProof":{"lemmas":[],"prop_name":"Z+x == x"}}],[43.882746,{"FailedProof":{"prop_name":"drop (length xs) (drop x xs) == []"}}],[43.882806,{"Discard":{"discarded":["drop (length xs) (drop x xs) == []","drop (length xs) (drop x xs) == []","drop (length xs) (drop x xs) == []","drop (length xs) (drop x xs) == []","drop (length xs) (drop x xs) == []","drop (length xs) (drop x xs) == []","drop (length xs) (drop x xs) == []","drop (length xs) (drop x xs) == []","drop (length xs) [] == []","drop (length xs) [] == []","drop (length xs) [] == []","drop (S x) [] == []","drop (S x) [] == []","drop (S x) [] == []","drop (x+x) [] == []","drop (x+x) [] == []","drop (x+x) [] == []","drop (S x) (y:[]) == []","drop (S x) (y:[]) == []","drop (S x) (y:[]) == []","drop (S x) (y:[]) == []","drop (S x) (y:[]) == []","drop (S x) (y:[]) == []","drop (S x) (x:[]) == []","drop (S x) (x:[]) == []","drop (S x) (x:[]) == []","drop (S Z) [] == []","drop (S x) (Z:[]) == []","drop (S x) (Z:[]) == []","drop (S x) (Z:[]) == []","drop (S Z) (x:[]) == []","drop (S Z) (x:[]) == []","drop (S Z) (x:[]) == []","drop (S Z) (Z:[]) == []","length [] == Z","Z+Z == Z","[]++(xs++ys) == xs++ys","drop Z (xs++ys) == xs++ys","(xs++ys)++[] == xs++ys","[]++(xs++ys) == xs++ys","drop Z (xs++ys) == xs++ys","(xs++ys)++[] == xs++ys","[]++(xs++ys) == xs++ys","drop Z (xs++ys) == xs++ys","(xs++ys)++[] == xs++ys","[]++(xs++ys) == xs++ys","drop Z (xs++ys) == xs++ys","(xs++ys)++[] == xs++ys","[]++(xs++ys) == xs++ys","drop Z (xs++ys) == xs++ys","(xs++ys)++[] == xs++ys","[]++(xs++ys) == xs++ys","drop Z (xs++ys) == xs++ys","(xs++ys)++[] == xs++ys","elem x (xs++xs) == elem x xs","elem x (xs++xs) == elem x xs","elem x (xs++xs) == elem x xs","elem x (xs++xs) == elem x xs","elem x (xs++xs) == elem x xs","elem x (xs++xs) == elem x xs","elem x (xs++xs) == elem x xs","elem x (xs++xs) == elem x xs","elem x (xs++xs) == elem x xs","[]++(x:xs) == x:xs","drop Z (x:xs) == x:xs","(x:xs)++[] == x:xs","(x:[])++xs == x:xs","[]++(x:xs) == x:xs","drop Z (x:xs) == x:xs","(x:xs)++[] == x:xs","(x:[])++xs == x:xs","[]++(x:xs) == x:xs","drop Z (x:xs) == x:xs","(x:xs)++[] == x:xs","(x:[])++xs == x:xs","[]++(x:xs) == x:xs","drop Z (x:xs) == x:xs","(x:xs)++[] == x:xs","(x:[])++xs == x:xs","[]++(x:xs) == x:xs","drop Z (x:xs) == x:xs","(x:xs)++[] == x:xs","(x:[])++xs == x:xs","[]++(x:xs) == x:xs","drop Z (x:xs) == x:xs","(x:xs)++[] == x:xs","(x:[])++xs == x:xs","[]++(x:xs) == x:xs","drop Z (x:xs) == x:xs","(x:xs)++[] == x:xs","(x:[])++xs == x:xs","[]++(x:xs) == x:xs","drop Z (x:xs) == x:xs","(x:xs)++[] == x:xs","(x:[])++xs == x:xs","[]++(x:xs) == x:xs","drop Z (x:xs) == x:xs","(x:xs)++[] == x:xs","(x:[])++xs == x:xs","drop (S x) (y:xs) == drop x xs","drop (S x) (y:xs) == drop x xs","[]++drop x xs == drop x xs","drop Z (drop x xs) == drop x xs","drop x xs++[] == drop x xs","drop (S x) (x:xs) == drop x xs","drop (S x) (Z:xs) == drop x xs","drop (S x) (y:xs) == drop x xs","drop (S x) (y:xs) == drop x xs","[]++drop x xs == drop x xs","drop Z (drop x xs) == drop x xs","drop x xs++[] == drop x xs","drop (S x) (x:xs) == drop x xs","drop (S x) (Z:xs) == drop x xs","drop (S x) (y:xs) == drop x xs","drop (S x) (y:xs) == drop x xs","[]++drop x xs == drop x xs","drop Z (drop x xs) == drop x xs","drop x xs++[] == drop x xs","drop (S x) (x:xs) == drop x xs","drop (S x) (Z:xs) == drop x xs","drop (S x) (y:xs) == drop x xs","drop (S x) (y:xs) == drop x xs","[]++drop x xs == drop x xs","drop Z (drop x xs) == drop x xs","drop x xs++[] == drop x xs","drop (S x) (x:xs) == drop x xs","drop (S x) (Z:xs) == drop x xs","drop (S x) (y:xs) == drop x xs","drop (S x) (y:xs) == drop x xs","[]++drop x xs == drop x xs","drop Z (drop x xs) == drop x xs","drop x xs++[] == drop x xs","drop (S x) (x:xs) == drop x xs","drop (S x) (Z:xs) == drop x xs","drop (S x) (y:xs) == drop x xs","drop (S x) (y:xs) == drop x xs","[]++drop x xs == drop x xs","drop Z (drop x xs) == drop x xs","drop x xs++[] == drop x xs","drop (S x) (x:xs) == drop x xs","drop (S x) (Z:xs) == drop x xs","drop (S x) (y:xs) == drop x xs","drop (S x) (y:xs) == drop x xs","[]++drop x xs == drop x xs","drop Z (drop x xs) == drop x xs","drop x xs++[] == drop x xs","drop (S x) (x:xs) == drop x xs","drop (S x) (Z:xs) == drop x xs","drop (S x) (y:xs) == drop x xs","drop (S x) (y:xs) == drop x xs","[]++drop x xs == drop x xs","drop Z (drop x xs) == drop x xs","drop x xs++[] == drop x xs","drop (S x) (x:xs) == drop x xs","drop (S x) (Z:xs) == drop x xs","drop (S x) (y:xs) == drop x xs","drop (S x) (y:xs) == drop x xs","[]++drop x xs == drop x xs","drop Z (drop x xs) == drop x xs","drop x xs++[] == drop x xs","drop (S x) (x:xs) == drop x xs","drop (S x) (Z:xs) == drop x xs","x+y == y+x","Z+(x+y) == x+y","(x+y)+Z == x+y","x+y == y+x","Z+(x+y) == x+y","(x+y)+Z == x+y","x+y == y+x","Z+(x+y) == x+y","(x+y)+Z == x+y","Z+length xs == length xs","length xs+Z == length xs","Z+length xs == length xs","length xs+Z == length xs","Z+length xs == length xs","length xs+Z == length xs","x+S Z == S x","Z+S x == S x","S x+Z == S x","x+S Z == S x","Z+S x == S x","S x+Z == S x","S Z+x == S x","x+S Z == S x","Z+S x == S x","S x+Z == S x","S Z+x == S x","[]++(xs++xs) == xs++xs","drop Z (xs++xs) == xs++xs","(xs++xs)++[] == xs++xs","[]++(xs++xs) == xs++xs","drop Z (xs++xs) == xs++xs","(xs++xs)++[] == xs++xs","[]++(xs++xs) == xs++xs","drop Z (xs++xs) == xs++xs","(xs++xs)++[] == xs++xs","Z+(x+x) == x+x","(x+x)+Z == x+x","Z+(x+x) == x+x","(x+x)+Z == x+x","Z+(x+x) == x+x","(x+x)+Z == x+x","elem x [] == elem y []","elem x [] == elem y []","elem Z [] == elem x []","elem (x+y) [] == elem x []","elem (x+y) [] == elem x []","elem (x+y) [] == elem z []","elem (length xs) [] == elem x []","elem (length xs) [] == elem x []","elem (length xs) [] == elem x []","elem (S x) [] == elem x []","elem (S x) [] == elem y []","elem (S x) [] == elem y []","elem (x+x) [] == elem x []","elem (x+x) [] == elem y []","elem (x+x) [] == elem y []"]}}],[43.910489,{"PlainProof":{"lemmas":[],"prop_name":"S Z+x == S x"}}],[44.911709,{"InductiveProof":{"lemmas":[],"prop_name":"elem (S x) (x:[]) == elem x []"}}],[44.912545,{"Discard":{"discarded":["elem (S x) (x:[]) == elem y []","elem (S x) (x:[]) == elem y []","elem (S Z) [] == elem x []","elem (S x) (Z:[]) == elem x []","elem (S x) (Z:[]) == elem y []","elem (S x) (Z:[]) == elem y []","elem (S Z) (Z:[]) == elem x []","[]++(x:[]) == x:[]","drop Z (x:[]) == x:[]","(x:[])++[] == x:[]","[]++(x:[]) == x:[]","drop Z (x:[]) == x:[]","(x:[])++[] == x:[]","[]++(x:[]) == x:[]","drop Z (x:[]) == x:[]","(x:[])++[] == x:[]","elem Z (xs++xs) == elem Z xs","elem Z (xs++xs) == elem Z xs","[]++(Z:xs) == Z:xs","drop Z (Z:xs) == Z:xs","(Z:xs)++[] == Z:xs","(Z:[])++xs == Z:xs","[]++(Z:xs) == Z:xs","drop Z (Z:xs) == Z:xs","(Z:xs)++[] == Z:xs","(Z:[])++xs == Z:xs","[]++(Z:xs) == Z:xs","drop Z (Z:xs) == Z:xs","(Z:xs)++[] == Z:xs","(Z:[])++xs == Z:xs","length (x:[]) == S Z","length (x:[]) == S Z","length (x:[]) == S Z","length (Z:[]) == S Z","Z+S Z == S Z","S Z+Z == S Z","[]++(Z:[]) == Z:[]","drop Z (Z:[]) == Z:[]","(Z:[])++[] == Z:[]","(xs++ys)++zs == xs++(ys++zs)","(xs++ys)++zs == xs++(ys++zs)","(xs++ys)++zs == xs++(ys++zs)","(xs++ys)++zs == xs++(ys++zs)","(xs++ys)++zs == xs++(ys++zs)","(xs++ys)++zs == xs++(ys++zs)","elem x (xs++ys) == elem x (ys++xs)","elem x (xs++ys) == elem x (ys++xs)","elem x (xs++ys) == elem x (ys++xs)","elem x (xs++ys) == elem x (ys++xs)","elem x (xs++ys) == elem x (ys++xs)","elem x (xs++ys) == elem x (ys++xs)","elem x (xs++ys) == elem x (ys++xs)","elem x (xs++ys) == elem x (ys++xs)","elem x (xs++ys) == elem x (ys++xs)","(x:xs)++ys == x:(xs++ys)","(x:[])++(xs++ys) == x:(xs++ys)","(x:xs)++ys == x:(xs++ys)","(x:[])++(xs++ys) == x:(xs++ys)","(x:xs)++ys == x:(xs++ys)","(x:[])++(xs++ys) == x:(xs++ys)","(x:xs)++ys == x:(xs++ys)","(x:[])++(xs++ys) == x:(xs++ys)","(x:xs)++ys == x:(xs++ys)","(x:[])++(xs++ys) == x:(xs++ys)","(x:xs)++ys == x:(xs++ys)","(x:[])++(xs++ys) == x:(xs++ys)","(x:[])++(y:xs) == x:(y:xs)","(x:[])++(y:xs) == x:(y:xs)","(x:[])++(y:xs) == x:(y:xs)","(x:[])++(y:xs) == x:(y:xs)","(x:[])++(y:xs) == x:(y:xs)","(x:[])++(y:xs) == x:(y:xs)","(x:[])++drop y xs == x:drop y xs","(x:[])++drop y xs == x:drop y xs","(x:[])++drop y xs == x:drop y xs","(x:[])++drop y xs == x:drop y xs","(x:[])++drop y xs == x:drop y xs","(x:[])++drop y xs == x:drop y xs","(x:xs)++ys == x:(xs++ys)","(x:[])++(xs++ys) == x:(xs++ys)","(x:xs)++ys == x:(xs++ys)","(x:[])++(xs++ys) == x:(xs++ys)","(x:xs)++ys == x:(xs++ys)","(x:[])++(xs++ys) == x:(xs++ys)","(x:xs)++ys == x:(xs++ys)","(x:[])++(xs++ys) == x:(xs++ys)","(x:xs)++ys == x:(xs++ys)","(x:[])++(xs++ys) == x:(xs++ys)","(x:xs)++ys == x:(xs++ys)","(x:[])++(xs++ys) == x:(xs++ys)","(x:[])++(y:xs) == x:(y:xs)","(x:[])++(y:xs) == x:(y:xs)","(x:[])++(y:xs) == x:(y:xs)","(x:[])++(y:xs) == x:(y:xs)","(x:[])++(y:xs) == x:(y:xs)","(x:[])++(y:xs) == x:(y:xs)","(x:[])++drop y xs == x:drop y xs","(x:[])++drop y xs == x:drop y xs","(x:[])++drop y xs == x:drop y xs","(x:[])++drop y xs == x:drop y xs","(x:[])++drop y xs == x:drop y xs","(x:[])++drop y xs == x:drop y xs","(x:xs)++ys == x:(xs++ys)","(x:[])++(xs++ys) == x:(xs++ys)","(x:xs)++ys == x:(xs++ys)","(x:[])++(xs++ys) == x:(xs++ys)","(x:xs)++ys == x:(xs++ys)","(x:[])++(xs++ys) == x:(xs++ys)","(x:xs)++ys == x:(xs++ys)","(x:[])++(xs++ys) == x:(xs++ys)","(x:xs)++ys == x:(xs++ys)","(x:[])++(xs++ys) == x:(xs++ys)","(x:xs)++ys == x:(xs++ys)","(x:[])++(xs++ys) == x:(xs++ys)","(x:[])++(y:xs) == x:(y:xs)","(x:[])++(y:xs) == x:(y:xs)","(x:[])++(y:xs) == x:(y:xs)","(x:[])++(y:xs) == x:(y:xs)","(x:[])++(y:xs) == x:(y:xs)","(x:[])++(y:xs) == x:(y:xs)","(x:[])++drop y xs == x:drop y xs","(x:[])++drop y xs == x:drop y xs","(x:[])++drop y xs == x:drop y xs","(x:[])++drop y xs == x:drop y xs","(x:[])++drop y xs == x:drop y xs","(x:[])++drop y xs == x:drop y xs","drop x (drop y xs) == drop y (drop x xs)","drop (x+y) xs == drop x (drop y xs)","drop x (drop y xs) == drop y (drop x xs)","drop (x+y) xs == drop x (drop y xs)","drop x (drop y xs) == drop y (drop x xs)","drop (x+y) xs == drop x (drop y xs)","drop x (drop y xs) == drop y (drop x xs)","drop (x+y) xs == drop x (drop y xs)","drop x (drop y xs) == drop y (drop x xs)","drop (x+y) xs == drop x (drop y xs)","drop x (drop y xs) == drop y (drop x xs)","drop (x+y) xs == drop x (drop y xs)","drop x (drop y xs) == drop y (drop x xs)","drop (x+y) xs == drop x (drop y xs)","drop x (drop y xs) == drop y (drop x xs)","drop (x+y) xs == drop x (drop y xs)","drop x (drop y xs) == drop y (drop x xs)","drop (x+y) xs == drop x (drop y xs)","x+(y+z) == y+(x+z)"]}}],[45.932772,{"FailedProof":{"prop_name":"elem Z (xs++xs) == elem Z xs"}}],[47.941525,{"FailedProof":{"prop_name":"z+(x+y) == x+(y+z)"}}],[48.950376,{"InductiveProof":{"lemmas":[],"prop_name":"(x+y)+z == x+(y+z)"}}],[51.042016,{"FailedProof":{"prop_name":"(x+z)+y == x+(y+z)"}}],[52.095372,{"InductiveProof":{"lemmas":[],"prop_name":"(y+z)+x == x+(y+z)"}}],[54.137833,{"FailedProof":{"prop_name":"elem (x+y) (xs++xs) == elem (x+y) xs"}}],[54.1379,{"Discard":{"discarded":["elem (x+y) (xs++xs) == elem (x+y) xs","elem (x+y) (xs++xs) == elem (x+y) xs","elem (x+y) (xs++xs) == elem (x+y) xs","elem (x+y) (xs++xs) == elem (x+y) xs","elem (x+y) (Z:xs) == elem (x+y) xs","elem (x+y) (xs++xs) == elem (x+y) xs","elem (x+y) (xs++xs) == elem (x+y) xs","elem (x+y) (xs++xs) == elem (x+y) xs"]}}],[56.189511,{"FailedProof":{"prop_name":"elem (x+z) (Z:xs) == elem (x+z) xs"}}],[59.388644,{"FailedProof":{"prop_name":"elem (y+z) (drop x zs) == elem (y+z) zs"}}],[59.388725,{"Discard":{"discarded":["elem (x+y) (xs++xs) == elem (x+y) xs","length (xs++ys) == length (ys++xs)","length xs+length ys == length (xs++ys)","length (xs++ys) == length (ys++xs)","length xs+length ys == length (xs++ys)","length xs+length ys == length (ys++xs)","length (xs++ys) == length (ys++xs)","length xs+length ys == length (xs++ys)","length xs+length ys == length (ys++xs)","length (x:xs) == length (y:xs)","length (x:xs) == length (y:xs)","S (length xs) == length (x:xs)","length (Z:xs) == length (x:xs)","length xs+S Z == length (x:xs)","S Z+length xs == length (x:xs)","length (x:xs) == length (y:xs)","length (x:xs) == length (y:xs)","S (length xs) == length (x:xs)","length (Z:xs) == length (x:xs)","length xs+S Z == length (x:xs)","S Z+length xs == length (x:xs)","length (x:xs) == length (y:xs)","length (x:xs) == length (y:xs)","S (length xs) == length (x:xs)","length (Z:xs) == length (x:xs)","length xs+S Z == length (x:xs)","S Z+length xs == length (x:xs)","x+S y == S (x+y)","x+S y == S (y+x)","S x+y == S (x+y)","S x+y == S (y+x)","(x+y)+S Z == S (x+y)","S Z+(x+y) == S (x+y)","x+S y == S (x+y)","x+S y == S (y+x)","S x+y == S (x+y)","S x+y == S (y+x)","(x+y)+S Z == S (x+y)","S Z+(x+y) == S (x+y)","x+S y == S (x+y)","x+S y == S (y+x)","S x+y == S (x+y)","S x+y == S (y+x)","(x+y)+S Z == S (x+y)","S Z+(x+y) == S (x+y)","(xs++xs)++ys == xs++(xs++ys)","(xs++xs)++ys == xs++(xs++ys)","(xs++ys)++xs == xs++(ys++xs)","(xs++ys)++xs == xs++(ys++xs)","(xs++ys)++ys == xs++(ys++ys)","(xs++ys)++ys == xs++(ys++ys)","(xs++ys)++xs == xs++(ys++xs)","(xs++xs)++ys == xs++(xs++ys)","(xs++xs)++ys == xs++(xs++ys)","(xs++ys)++xs == xs++(ys++xs)","(xs++ys)++ys == xs++(ys++ys)","(xs++ys)++ys == xs++(ys++ys)","(xs++ys)++xs == xs++(ys++xs)","(xs++ys)++xs == xs++(ys++xs)","(xs++xs)++ys == xs++(xs++ys)","(xs++xs)++ys == xs++(xs++ys)","(xs++ys)++ys == xs++(ys++ys)","(xs++ys)++ys == xs++(ys++ys)","elem x (x:xs) == elem x (x:ys)","elem x (x:xs) == elem x (x:ys)","elem x (x:xs) == elem y (y:xs)"]}}],[59.447775,{"PlainProof":{"lemmas":[],"prop_name":"length ys+length xs == length (xs++ys)"}}],[62.482085,{"FailedProof":{"prop_name":"elem y (y:ys) == elem x (x:xs)"}}],[62.482183,{"Discard":{"discarded":["elem x (x:xs) == elem y (y:ys)","elem x (x:xs) == elem y (y:xs)","elem x (x:xs) == elem y (y:ys)","elem x (x:xs) == elem y (y:ys)"]}}],[64.497025,{"FailedProof":{"prop_name":"elem x (x:[]) == elem x (x:xs)"}}],[66.524528,{"FailedProof":{"prop_name":"elem y (y:[]) == elem x (x:xs)"}}],[66.524624,{"Discard":{"discarded":["elem x (x:[]) == elem y (y:xs)"]}}],[68.538928,{"FailedProof":{"prop_name":"elem Z (Z:xs) == elem x (x:xs)"}}],[70.54762,{"FailedProof":{"prop_name":"elem Z (Z:ys) == elem x (x:xs)"}}],[70.54769,{"Discard":{"discarded":["elem Z (Z:xs) == elem x (x:ys)","(x:[])++(x:xs) == x:(x:xs)","(x:[])++(x:xs) == x:(x:xs)","(x:[])++(x:xs) == x:(x:xs)","(x:[])++drop x xs == x:drop x xs","(x:[])++drop x xs == x:drop x xs","(x:[])++drop x xs == x:drop x xs","(x:xs)++xs == x:(xs++xs)","(x:[])++(xs++xs) == x:(xs++xs)","(x:xs)++xs == x:(xs++xs)","(x:[])++(xs++xs) == x:(xs++xs)","(x:xs)++xs == x:(xs++xs)","(x:[])++(xs++xs) == x:(xs++xs)","(x:[])++(x:xs) == x:(x:xs)","(x:[])++(x:xs) == x:(x:xs)","(x:[])++(x:xs) == x:(x:xs)","(x:[])++drop x xs == x:drop x xs","(x:[])++drop x xs == x:drop x xs","(x:[])++drop x xs == x:drop x xs","(x:xs)++xs == x:(xs++xs)","(x:[])++(xs++xs) == x:(xs++xs)","(x:xs)++xs == x:(xs++xs)","(x:[])++(xs++xs) == x:(xs++xs)","(x:xs)++xs == x:(xs++xs)","(x:[])++(xs++xs) == x:(xs++xs)","(x:[])++(x:xs) == x:(x:xs)","(x:[])++(x:xs) == x:(x:xs)","(x:[])++(x:xs) == x:(x:xs)","(x:[])++drop x xs == x:drop x xs","(x:[])++drop x xs == x:drop x xs","(x:[])++drop x xs == x:drop x xs","(x:xs)++xs == x:(xs++xs)","(x:[])++(xs++xs) == x:(xs++xs)","(x:xs)++xs == x:(xs++xs)","(x:[])++(xs++xs) == x:(xs++xs)","(x:xs)++xs == x:(xs++xs)","(x:[])++(xs++xs) == x:(xs++xs)","drop x (Z:xs) == drop x (x:xs)","drop x (Z:xs) == drop x (x:xs)","drop x (Z:xs) == drop x (x:xs)"]}}],[72.562457,{"FailedProof":{"prop_name":"elem Z (Z:[]) == elem x (x:xs)"}}],[73.574858,{"FailedProof":{"prop_name":"drop (x+x) xs == drop x (drop x xs)"}}],[73.574932,{"Discard":{"discarded":["drop (x+x) xs == drop x (drop x xs)","drop (x+x) xs == drop x (drop x xs)","drop x (Z:xs) == drop x (x:xs)","drop x (Z:xs) == drop x (x:xs)","drop x (Z:xs) == drop x (x:xs)","drop (x+x) xs == drop x (drop x xs)","drop (x+x) xs == drop x (drop x xs)","drop (x+x) xs == drop x (drop x xs)","drop x (Z:xs) == drop x (x:xs)","drop x (Z:xs) == drop x (x:xs)","drop x (Z:xs) == drop x (x:xs)","drop (x+x) xs == drop x (drop x xs)","drop (x+x) xs == drop x (drop x xs)","drop (x+x) xs == drop x (drop x xs)","x+(y+y) == y+(y+x)","(x+y)+x == x+(x+y)","(x+x)+y == x+(x+y)","x+(y+y) == y+(y+x)","(x+y)+x == x+(x+y)","(x+x)+y == x+(x+y)","length xs+x == x+length xs","length xs+x == x+length xs","length xs+x == x+length xs","x+(y+x) == y+(x+x)","(x+y)+y == x+(y+y)","(x+x)+y == y+(x+x)","x+(y+x) == y+(x+x)","(x+y)+y == x+(y+y)","(x+x)+y == y+(x+x)","x+(y+y) == y+(y+x)","(x+y)+x == x+(x+y)","(x+x)+y == x+(x+y)","length xs+x == x+length xs","length xs+x == x+length xs","length xs+x == x+length xs","x+(y+x) == y+(x+x)","(x+y)+y == x+(y+y)","(x+x)+y == y+(x+x)","length xs+x == x+length xs","length xs+x == x+length xs","length xs+x == x+length xs","elem (length xs) (ys++ys) == elem (length xs) ys","elem (length xs) (ys++ys) == elem (length xs) ys","elem (length xs) (ys++ys) == elem (length xs) ys","elem (length xs) (ys++ys) == elem (length xs) ys","elem (length xs) (ys++ys) == elem (length xs) ys","elem (S x) (x:xs) == elem (S x) xs"]}}],[75.588437,{"FailedProof":{"prop_name":"elem (length xs) (ys++ys) == elem (length xs) ys"}}],[76.603016,{"FailedProof":{"prop_name":"elem (S x) (xs++xs) == elem (S x) xs"}}],[76.603116,{"Discard":{"discarded":["elem (S x) (Z:xs) == elem (S x) xs","elem (S x) (x:xs) == elem (S x) xs","elem (S x) (xs++xs) == elem (S x) xs","elem (S x) (Z:xs) == elem (S x) xs","elem (S x) (x:xs) == elem (S x) xs","elem (S x) (xs++xs) == elem (S x) xs","elem (S x) (Z:xs) == elem (S x) xs","elem (S x) (x:xs) == elem (S x) xs","elem (S x) (xs++xs) == elem (S x) xs","elem (S x) (Z:xs) == elem (S x) xs","elem (S x) (x:xs) == elem (S x) xs","elem (S x) (xs++xs) == elem (S x) xs","elem (S x) (Z:xs) == elem (S x) xs","elem (S x) (x:xs) == elem (S x) xs","elem (S x) (xs++xs) == elem (S x) xs","elem (S x) (Z:xs) == elem (S x) xs","elem (S x) (x:xs) == elem (S x) xs","elem (S x) (xs++xs) == elem (S x) xs","elem (S x) (Z:xs) == elem (S x) xs","elem (S x) (x:xs) == elem (S x) xs","elem (S x) (xs++xs) == elem (S x) xs","elem (S x) (Z:xs) == elem (S x) xs","elem (S x) (x:xs) == elem (S x) xs","elem (S x) (xs++xs) == elem (S x) xs","elem (S x) (Z:xs) == elem (S x) xs","elem (x+x) (xs++xs) == elem (x+x) xs","elem (x+x) (xs++xs) == elem (x+x) xs","elem (x+x) (xs++xs) == elem (x+x) xs","elem (x+x) (xs++xs) == elem (x+x) xs","elem (x+x) (xs++xs) == elem (x+x) xs","elem (x+x) (xs++xs) == elem (x+x) xs","elem (x+x) (xs++xs) == elem (x+x) xs","elem (x+x) (xs++xs) == elem (x+x) xs"]}}],[78.616191,{"FailedProof":{"prop_name":"elem (x+x) (xs++xs) == elem (x+x) xs"}}],[79.630081,{"FailedProof":{"prop_name":"drop (S Z) (drop x xs) == drop (S x) xs"}}],[79.630137,{"Discard":{"discarded":["drop (S Z) (drop x xs) == drop (S x) xs","drop (S Z) (drop x xs) == drop (S x) xs","drop (S Z) (drop x xs) == drop (S x) xs","drop (S Z) (drop x xs) == drop (S x) xs","drop (S Z) (drop x xs) == drop (S x) xs","drop (S Z) (drop x xs) == drop (S x) xs","drop (S Z) (drop x xs) == drop (S x) xs","drop (S Z) (drop x xs) == drop (S x) xs","length xs+length xs == length (xs++xs)","length xs+length xs == length (xs++xs)","length xs+length xs == length (xs++xs)","S x+S Z == S (S x)","S Z+S x == S (S x)","S x+S Z == S (S x)","S Z+S x == S (S x)","S x+S Z == S (S x)","S Z+S x == S (S x)","x+S x == S (x+x)","S x+x == S (x+x)","(x+x)+S Z == S (x+x)","S Z+(x+x) == S (x+x)","x+S x == S (x+x)","S x+x == S (x+x)","(x+x)+S Z == S (x+x)","S Z+(x+x) == S (x+x)","x+S x == S (x+x)","S x+x == S (x+x)","(x+x)+S Z == S (x+x)","S Z+(x+x) == S (x+x)","(xs++xs)++xs == xs++(xs++xs)","(xs++xs)++xs == xs++(xs++xs)","(xs++xs)++xs == xs++(xs++xs)","(x+x)+x == x+(x+x)","(x+x)+x == x+(x+x)","(x+x)+x == x+(x+x)","elem (length xs) (xs++xs) == elem (length xs) xs","elem (length xs) (xs++xs) == elem (length xs) xs"]}}],[80.645524,{"FailedProof":{"prop_name":"elem (length xs) (xs++xs) == elem (length xs) xs"}}],[83.691291,{"FailedProof":{"prop_name":"elem (x+y) (ys++xs) == elem (x+y) (xs++ys)"}}],[83.691362,{"Discard":{"discarded":["elem (x+y) (xs++ys) == elem (x+y) (ys++xs)","elem (x+y) (xs++ys) == elem (x+y) (ys++xs)","elem (x+y) (xs++ys) == elem (x+y) (ys++xs)","elem (x+y) (xs++ys) == elem (x+y) (ys++xs)","elem (x+y) (xs++ys) == elem (x+y) (ys++xs)","elem (x+y) (xs++ys) == elem (x+y) (ys++xs)","elem (x+y) (xs++ys) == elem (x+y) (ys++xs)","elem (x+y) (xs++ys) == elem (x+y) (ys++xs)"]}}],[86.799497,{"FailedProof":{"prop_name":"drop (x+z) (drop y xs) == drop (x+y) (drop z xs)"}}],[88.952705,{"FailedProof":{"prop_name":"drop (y+z) (drop x xs) == drop (x+y) (drop z xs)"}}],[88.952794,{"Discard":{"discarded":["drop (x+y) (drop z xs) == drop (x+z) (drop y xs)","drop (x+y) (drop z xs) == drop (z+x) (drop y xs)","drop (x+y) (drop z xs) == drop (x+z) (drop y xs)","drop (x+y) (drop z xs) == drop (z+x) (drop y xs)","drop (x+y) (y:xs) == drop (x+y) (x:xs)","drop (x+y) (y:xs) == drop (x+y) (x:xs)","drop (x+y) (Z:xs) == drop (x+y) (x:xs)","drop (x+y) (y:xs) == drop (x+y) (x:xs)","drop (x+y) (Z:xs) == drop (x+y) (x:xs)"]}}],[90.970793,{"FailedProof":{"prop_name":"drop (x+y) (Z:xs) == drop (x+y) (x:xs)"}}],[93.102556,{"FailedProof":{"prop_name":"drop (x+x) (drop y xs) == drop (x+y) (drop x xs)"}}],[93.102668,{"Discard":{"discarded":["drop (x+x) (drop y xs) == drop (x+y) (drop x xs)","drop (x+x) (drop y xs) == drop (x+y) (drop x xs)","drop (x+x) (drop y xs) == drop (y+x) (drop x xs)","drop (x+x) (drop y xs) == drop (y+x) (drop x xs)","drop (x+y) (y:xs) == drop (x+y) (x:xs)","drop (x+y) (Z:xs) == drop (x+y) (x:xs)","drop (x+y) (y:xs) == drop (x+y) (x:xs)","drop (x+y) (Z:xs) == drop (x+y) (x:xs)","drop (x+y) (y:xs) == drop (x+y) (x:xs)","drop (x+y) (Z:xs) == drop (x+y) (x:xs)","drop (x+x) (drop y xs) == drop (x+y) (drop x xs)","drop (x+x) (drop y xs) == drop (x+y) (drop x xs)","drop (x+x) (drop y xs) == drop (x+y) (drop x xs)","drop (x+x) (drop y xs) == drop (y+x) (drop x xs)","drop (x+x) (drop y xs) == drop (y+x) (drop x xs)","drop (x+x) (drop y xs) == drop (y+x) (drop x xs)","drop (x+y) (y:xs) == drop (x+y) (x:xs)","drop (x+y) (Z:xs) == drop (x+y) (x:xs)","drop (x+y) (y:xs) == drop (x+y) (x:xs)","drop (x+y) (Z:xs) == drop (x+y) (x:xs)","drop (x+y) (y:xs) == drop (x+y) (x:xs)","drop (x+y) (Z:xs) == drop (x+y) (x:xs)","drop (x+x) (drop y xs) == drop (x+y) (drop x xs)","drop (x+x) (drop y xs) == drop (x+y) (drop x xs)","drop (x+x) (drop y xs) == drop (x+y) (drop x xs)","drop (x+x) (drop y xs) == drop (y+x) (drop x xs)","drop (x+x) (drop y xs) == drop (y+x) (drop x xs)","drop (x+x) (drop y xs) == drop (y+x) (drop x xs)","(x+y)+(x+z) == (x+z)+(x+y)","(x+y)+(z+z) == (z+x)+(z+y)","(x+x)+(y+z) == (x+y)+(x+z)","(x+y)+(z+z) == (x+z)+(z+y)","(x+y)+(z+x) == (z+x)+(x+y)","(x+x)+(y+z) == (y+x)+(x+z)","length xs+(x+y) == (x+y)+length xs","length xs+(x+y) == (x+y)+length xs","length xs+(x+y) == (x+y)+length xs","(x+y)+S z == (x+z)+S y","(x+y)+S z == (z+x)+S y","S x+(y+z) == (x+y)+S z","S x+(y+z) == (y+x)+S z","S x+(y+z) == (y+z)+S x","(x+y)+(z+y) == (x+z)+(y+y)","(x+y)+(z+y) == (z+x)+(y+y)","(x+x)+(y+z) == (y+z)+(x+x)","length xs+(x+y) == (x+y)+length xs","length xs+(x+y) == (x+y)+length xs","length xs+(x+y) == (x+y)+length xs","length xs+(x+y) == (x+y)+length xs","length xs+(x+y) == (x+y)+length xs","length xs+(x+y) == (x+y)+length xs"]}}],[95.25381,{"FailedProof":{"prop_name":"drop (y+y) (drop x xs) == drop (x+y) (drop y xs)"}}],[97.269714,{"FailedProof":{"prop_name":"elem (length xs) (zs++ys) == elem (length xs) (ys++zs)"}}],[97.269793,{"Discard":{"discarded":["elem (length xs) (ys++zs) == elem (length xs) (zs++ys)","elem (length xs) (ys++zs) == elem (length xs) (zs++ys)","elem (S x) (xs++ys) == elem (S x) (ys++xs)","elem (S x) (xs++ys) == elem (S x) (ys++xs)","elem (S x) (xs++ys) == elem (S x) (ys++xs)","elem (S x) (xs++ys) == elem (S x) (ys++xs)","elem (S x) (xs++ys) == elem (S x) (ys++xs)","elem (S x) (xs++ys) == elem (S x) (ys++xs)","elem (S x) (xs++ys) == elem (S x) (ys++xs)","elem (S x) (xs++ys) == elem (S x) (ys++xs)"]}}],[99.299847,{"FailedProof":{"prop_name":"elem (S x) (ys++xs) == elem (S x) (xs++ys)"}}],[101.338007,{"FailedProof":{"prop_name":"elem (x+x) (ys++xs) == elem (x+x) (xs++ys)"}}],[101.338111,{"Discard":{"discarded":["elem (x+x) (xs++ys) == elem (x+x) (ys++xs)","elem (x+x) (xs++ys) == elem (x+x) (ys++xs)","elem (x+x) (xs++ys) == elem (x+x) (ys++xs)","elem (x+x) (xs++ys) == elem (x+x) (ys++xs)","elem (x+x) (xs++ys) == elem (x+x) (ys++xs)","elem (x+x) (xs++ys) == elem (x+x) (ys++xs)","elem (x+x) (xs++ys) == elem (x+x) (ys++xs)","elem (x+x) (xs++ys) == elem (x+x) (ys++xs)"]}}],[103.371639,{"FailedProof":{"prop_name":"elem (y+y) (drop y xs) == elem (y+y) (drop x xs)"}}],[105.390263,{"FailedProof":{"prop_name":"drop (S y) (drop x xs) == drop (S x) (drop y xs)"}}],[105.390333,{"Discard":{"discarded":["drop (S x) (drop y xs) == drop (S y) (drop x xs)","drop (S x) (drop y xs) == drop (S y) (drop x xs)","drop (S x) (drop y xs) == drop (S y) (drop x xs)","drop (S x) (drop y xs) == drop (S y) (drop x xs)","drop (S x) (drop y xs) == drop (S y) (drop x xs)","drop (S x) (drop y xs) == drop (S y) (drop x xs)","drop (S x) (drop y xs) == drop (S y) (drop x xs)","drop (S x) (drop y xs) == drop (S y) (drop x xs)","elem x (y:[]) == elem y (x:[])","elem x (y:[]) == elem y (x:[])","elem x (y:[]) == elem y (x:[])","(x:[])++(y:[]) == x:(y:[])","(x:[])++(y:[]) == x:(y:[])","(x:[])++(Z:xs) == x:(Z:xs)","(x:[])++(Z:xs) == x:(Z:xs)","(x:[])++(Z:xs) == x:(Z:xs)","(x:[])++(y:[]) == x:(y:[])","(x:[])++(y:[]) == x:(y:[])","(x:[])++(Z:xs) == x:(Z:xs)","(x:[])++(Z:xs) == x:(Z:xs)","(x:[])++(Z:xs) == x:(Z:xs)","(x:[])++(y:[]) == x:(y:[])","(x:[])++(y:[]) == x:(y:[])","(x:[])++(Z:xs) == x:(Z:xs)","(x:[])++(Z:xs) == x:(Z:xs)","(x:[])++(Z:xs) == x:(Z:xs)","drop (x+x) (y:[]) == drop x (y:[])","drop (x+x) (y:[]) == drop x (y:[])","drop (x+x) (y:[]) == drop x (y:[])","drop (x+x) (y:[]) == drop x (y:[])","drop (x+x) (y:[]) == drop x (y:[])","drop (x+x) (y:[]) == drop x (y:[])","elem Z (xs++ys) == elem Z (ys++xs)","elem Z (xs++ys) == elem Z (ys++xs)","(Z:xs)++ys == Z:(xs++ys)","(Z:[])++(xs++ys) == Z:(xs++ys)","(Z:xs)++ys == Z:(xs++ys)","(Z:[])++(xs++ys) == Z:(xs++ys)","(Z:xs)++ys == Z:(xs++ys)","(Z:[])++(xs++ys) == Z:(xs++ys)","(Z:xs)++ys == Z:(xs++ys)","(Z:[])++(xs++ys) == Z:(xs++ys)","(Z:xs)++ys == Z:(xs++ys)","(Z:[])++(xs++ys) == Z:(xs++ys)","(Z:xs)++ys == Z:(xs++ys)","(Z:[])++(xs++ys) == Z:(xs++ys)","(Z:[])++(x:xs) == Z:(x:xs)","(Z:[])++(x:xs) == Z:(x:xs)","(Z:[])++(x:xs) == Z:(x:xs)","(Z:[])++(x:xs) == Z:(x:xs)","(Z:[])++(x:xs) == Z:(x:xs)","(Z:[])++(x:xs) == Z:(x:xs)","(Z:[])++(x:xs) == Z:(x:xs)","(Z:[])++(x:xs) == Z:(x:xs)","(Z:[])++(x:xs) == Z:(x:xs)","(Z:[])++drop x xs == Z:drop x xs","(Z:[])++drop x xs == Z:drop x xs","(Z:[])++drop x xs == Z:drop x xs","(Z:[])++drop x xs == Z:drop x xs","(Z:[])++drop x xs == Z:drop x xs","(Z:[])++drop x xs == Z:drop x xs","(Z:[])++drop x xs == Z:drop x xs","(Z:[])++drop x xs == Z:drop x xs","(Z:[])++drop x xs == Z:drop x xs","(x+x)+(y+y) == (x+y)+(x+y)","(x+x)+(y+y) == (y+x)+(y+x)","S x+(x+y) == (x+y)+S x","S x+(y+y) == (y+x)+S y","(x+x)+S y == (x+y)+S x","S x+(y+y) == (x+y)+S y","S x+(y+x) == (y+x)+S x","(x+x)+S y == (y+x)+S x","(x+x)+(x+y) == (x+y)+(x+x)","(x+x)+(y+x) == (y+x)+(x+x)","(x+x)+(y+y) == (x+y)+(x+y)","(x+x)+(y+y) == (y+x)+(y+x)","S x+(x+y) == (x+y)+S x","S x+(y+y) == (y+x)+S y","(x+x)+S y == (x+y)+S x","S x+(y+y) == (x+y)+S y","S x+(y+x) == (y+x)+S x","(x+x)+S y == (y+x)+S x","(x+x)+(x+y) == (x+y)+(x+x)","(x+x)+(y+x) == (y+x)+(x+x)","(x+x)+(y+y) == (x+y)+(x+y)","(x+x)+(y+y) == (y+x)+(y+x)","S x+(x+y) == (x+y)+S x","S x+(y+y) == (y+x)+S y","(x+x)+S y == (x+y)+S x","S x+(y+y) == (x+y)+S y","S x+(y+x) == (y+x)+S x","(x+x)+S y == (y+x)+S x","(x+x)+(x+y) == (x+y)+(x+x)","(x+x)+(y+x) == (y+x)+(x+x)"]}}],[107.718443,{"FailedProof":{"prop_name":"elem Z (ys++xs) == elem Z (xs++ys)"}}],[108.730857,{"FailedProof":{"prop_name":"elem (length xs) (ys++xs) == elem (length xs) (xs++ys)"}}],[108.73094,{"Discard":{"discarded":["elem (length xs) (ys++xs) == elem (length xs) (xs++ys)","elem (length xs) (ys++xs) == elem (length xs) (xs++ys)","elem (length xs) (xs++ys) == elem (length xs) (ys++xs)","elem (length xs) (xs++ys) == elem (length xs) (ys++xs)","elem (x+x) (Z:xs) == elem (x+x) (x:xs)","elem (x+x) (Z:xs) == elem (x+x) (x:xs)","elem (x+x) (Z:xs) == elem (x+x) (x:xs)","elem (x+x) (Z:xs) == elem (x+x) (x:xs)","elem (x+x) (Z:xs) == elem (x+x) (x:xs)","elem (x+x) (Z:xs) == elem (x+x) (x:xs)","elem (x+x) (Z:xs) == elem (x+x) (x:xs)","elem (x+x) (Z:xs) == elem (x+x) (x:xs)","elem (x+x) (Z:xs) == elem (x+x) (x:xs)"]}}],[110.753166,{"FailedProof":{"prop_name":"elem (length ys) (ys++xs) == elem (length ys) (xs++ys)"}}],[111.756532,{"FailedProof":{"prop_name":"drop (x+x) (Z:xs) == drop (x+x) (x:xs)"}}],[111.756614,{"Discard":{"discarded":["drop (x+x) (Z:xs) == drop (x+x) (x:xs)","drop (x+x) (Z:xs) == drop (x+x) (x:xs)","drop (x+x) (Z:xs) == drop (x+x) (x:xs)","drop (x+x) (Z:xs) == drop (x+x) (x:xs)","drop (x+x) (Z:xs) == drop (x+x) (x:xs)","drop (x+x) (Z:xs) == drop (x+x) (x:xs)","drop (x+x) (Z:xs) == drop (x+x) (x:xs)","drop (x+x) (Z:xs) == drop (x+x) (x:xs)","S x+length xs == length xs+S x","S x+length xs == length xs+S x","(x+x)+length xs == length xs+(x+x)","(x+x)+length xs == length xs+(x+x)","(x+x)+length xs == length xs+(x+x)","S x+length xs == length xs+S x","S x+length xs == length xs+S x","S x+length xs == length xs+S x","(x+x)+length xs == length xs+(x+x)","(x+x)+length xs == length xs+(x+x)","(x+x)+length xs == length xs+(x+x)","S x+length xs == length xs+S x","S x+length xs == length xs+S x","S x+length xs == length xs+S x","(x+x)+length xs == length xs+(x+x)","(x+x)+length xs == length xs+(x+x)","(x+x)+length xs == length xs+(x+x)","S x+S y == S y+S x","S x+S y == S y+S x","S x+S y == S y+S x","(x:[])++(x:[]) == x:(x:[])","(x:[])++(x:[]) == x:(x:[])","(x:[])++(x:[]) == x:(x:[])","drop x (Z:[]) == drop x (x:[])","drop (x+x) (x:[]) == drop x (x:[])","drop (x+x) (Z:[]) == drop x (x:[])","drop x (Z:[]) == drop x (x:[])","drop (x+x) (x:[]) == drop x (x:[])","drop (x+x) (Z:[]) == drop x (x:[])","drop x (Z:[]) == drop x (x:[])","drop (x+x) (x:[]) == drop x (x:[])","drop (x+x) (Z:[]) == drop x (x:[])","(Z:xs)++xs == Z:(xs++xs)","(Z:[])++(xs++xs) == Z:(xs++xs)","(Z:xs)++xs == Z:(xs++xs)","(Z:[])++(xs++xs) == Z:(xs++xs)","(Z:xs)++xs == Z:(xs++xs)","(Z:[])++(xs++xs) == Z:(xs++xs)","(x+x)+S x == S x+(x+x)","(x+x)+S x == S x+(x+x)","(x+x)+S x == S x+(x+x)"]}}],[112.252484,{"PlainProof":{"lemmas":[],"prop_name":"S x+length xs == length xs+S x"}}],[113.263636,{"FailedProof":{"prop_name":"elem (S Z) (xs++xs) == elem (S Z) xs"}}],[113.264014,{"Discard":{"discarded":["elem (S Z) (Z:xs) == elem (S Z) xs","elem (S Z) (xs++xs) == elem (S Z) xs","elem (S Z) (Z:xs) == elem (S Z) xs","elem (S Z) (xs++xs) == elem (S Z) xs","elem (S Z) (Z:xs) == elem (S Z) xs","S Z+S Z == S (S Z)"]}}],[115.28178,{"FailedProof":{"prop_name":"elem (y+z) (z:[]) == elem (x+y) (x:[])"}}],[117.289849,{"FailedProof":{"prop_name":"elem y (Z:[]) == elem (x+y) (x:[])"}}],[119.412023,{"FailedProof":{"prop_name":"elem Z (y:[]) == elem (x+y) (x:[])"}}],[120.417544,{"FailedProof":{"prop_name":"elem (y+y) (y:[]) == elem (x+y) (x:[])"}}],[120.417687,{"Discard":{"discarded":["elem (x+y) (y:[]) == elem (x+z) (z:[])"]}}],[122.431049,{"FailedProof":{"prop_name":"elem (y+y) (Z:[]) == elem (x+y) (x:[])"}}],[123.437191,{"FailedProof":{"prop_name":"elem x (Z:[]) == elem (x+y) (y:[])"}}],[125.453837,{"FailedProof":{"prop_name":"elem Z (x:[]) == elem (x+y) (y:[])"}}],[126.458574,{"FailedProof":{"prop_name":"elem (x+x) (x:[]) == elem (x+y) (y:[])"}}],[128.771668,{"FailedProof":{"prop_name":"elem (x+x) (Z:[]) == elem (x+y) (y:[])"}}],[130.809902,{"FailedProof":{"prop_name":"elem (y+z) (y:[]) == elem (x+z) (x:[])"}}],[130.80998,{"Discard":{"discarded":["elem x (Z:[]) == elem (y+x) (y:[])","elem Z (x:[]) == elem (y+x) (y:[])","elem (x+x) (x:[]) == elem (y+x) (y:[])","elem (x+x) (Z:[]) == elem (y+x) (y:[])","drop (x+y) (y:[]) == drop (x+y) (x:[])","drop (x+y) (y:[]) == drop (x+y) (x:[])","drop (x+y) (Z:[]) == drop (x+y) (x:[])","drop (x+y) (y:[]) == drop (x+y) (x:[])","drop (x+y) (Z:[]) == drop (x+y) (x:[])"]}}],[132.828199,{"FailedProof":{"prop_name":"drop (x+y) (Z:[]) == drop (x+y) (x:[])"}}],[133.84128,{"FailedProof":{"prop_name":"elem (S Z) (ys++xs) == elem (S Z) (xs++ys)"}}],[133.841355,{"Discard":{"discarded":["elem (S Z) (xs++ys) == elem (S Z) (ys++xs)","elem (S Z) (xs++ys) == elem (S Z) (ys++xs)","(x:[])++(Z:[]) == x:(Z:[])","(x:[])++(Z:[]) == x:(Z:[])","(x:[])++(Z:[]) == x:(Z:[])","(Z:[])++(x:[]) == Z:(x:[])","(Z:[])++(x:[]) == Z:(x:[])","(Z:[])++(x:[]) == Z:(x:[])","(Z:[])++(Z:xs) == Z:(Z:xs)","(Z:[])++(Z:xs) == Z:(Z:xs)","(Z:[])++(Z:xs) == Z:(Z:xs)","(Z:[])++(Z:[]) == Z:(Z:[])"]}}],[133.841522,{"Discard":{"discarded":["x+y == y+x"]}}],[135.864035,{"FailedProof":{"prop_name":"elem x (ys++xs) == elem x (xs++ys)"}}],[137.882533,{"FailedProof":{"prop_name":"drop y (drop x xs) == drop x (drop y xs)"}}],[137.882563,{"Discard":{"discarded":["x+(y+z) == y+(x+z)","length (xs++ys) == length (ys++xs)"]}}],[140.233686,{"FailedProof":{"prop_name":"drop (x+y) xs == drop x (drop y xs)"}}],[142.242696,{"FailedProof":{"prop_name":"elem x (x:ys) == elem x (x:xs)"}}],[144.255223,{"FailedProof":{"prop_name":"elem x (xs++xs) == elem x xs"}}],[146.290899,{"FailedProof":{"prop_name":"elem y (y:xs) == elem x (x:xs)"}}],[147.988972,{"PlainProof":{"lemmas":[],"prop_name":"elem (S x) (x:xs) == elem (S x) xs"}}],[148.385988,{"FailedProof":{"prop_name":"elem y (x:[]) == elem x (y:[])"}}],[150.721718,{"FailedProof":{"prop_name":"elem (x+z) (z:[]) == elem (x+y) (y:[])"}}],[152.707229,{"FailedProof":{"prop_name":"elem (x+x) (Z:xs) == elem (x+x) (x:xs)"}}],[154.728332,{"FailedProof":{"prop_name":"drop (length xs) (drop x xs) == []"}}],[155.73738,{"FailedProof":{"prop_name":"elem Z (xs++xs) == elem Z xs"}}],[155.737414,{"Discard":{"discarded":["x+(y+z) == y+(z+x)","(x+y)+z == x+(z+y)"]}}],[157.787762,{"FailedProof":{"prop_name":"elem (x+y) (xs++xs) == elem (x+y) xs"}}],[160.101553,{"FailedProof":{"prop_name":"elem (x+z) (Z:xs) == elem (x+z) xs"}}],[163.292316,{"FailedProof":{"prop_name":"elem (y+z) (drop x zs) == elem (y+z) zs"}}],[165.343353,{"FailedProof":{"prop_name":"elem y (y:ys) == elem x (x:xs)"}}],[167.355796,{"FailedProof":{"prop_name":"elem x (x:[]) == elem x (x:xs)"}}],[169.383232,{"FailedProof":{"prop_name":"elem y (y:[]) == elem x (x:xs)"}}],[171.414612,{"FailedProof":{"prop_name":"elem Z (Z:xs) == elem x (x:xs)"}}],[173.424212,{"FailedProof":{"prop_name":"elem Z (Z:ys) == elem x (x:xs)"}}],[175.437012,{"FailedProof":{"prop_name":"elem Z (Z:[]) == elem x (x:xs)"}}],[176.452089,{"FailedProof":{"prop_name":"drop (x+x) xs == drop x (drop x xs)"}}],[178.468655,{"FailedProof":{"prop_name":"elem (length xs) (ys++ys) == elem (length xs) ys"}}],[179.479822,{"FailedProof":{"prop_name":"elem (S x) (xs++xs) == elem (S x) xs"}}],[181.49166,{"FailedProof":{"prop_name":"elem (x+x) (xs++xs) == elem (x+x) xs"}}],[182.505573,{"FailedProof":{"prop_name":"drop (S Z) (drop x xs) == drop (S x) xs"}}],[183.520925,{"FailedProof":{"prop_name":"elem (length xs) (xs++xs) == elem (length xs) xs"}}],[186.561616,{"FailedProof":{"prop_name":"elem (x+y) (ys++xs) == elem (x+y) (xs++ys)"}}],[189.688197,{"FailedProof":{"prop_name":"drop (x+z) (drop y xs) == drop (x+y) (drop z xs)"}}],[191.833777,{"FailedProof":{"prop_name":"drop (y+z) (drop x xs) == drop (x+y) (drop z xs)"}}],[193.851488,{"FailedProof":{"prop_name":"drop (x+y) (Z:xs) == drop (x+y) (x:xs)"}}],[195.983022,{"FailedProof":{"prop_name":"drop (x+x) (drop y xs) == drop (x+y) (drop x xs)"}}],[198.131844,{"FailedProof":{"prop_name":"drop (y+y) (drop x xs) == drop (x+y) (drop y xs)"}}],[200.149874,{"FailedProof":{"prop_name":"elem (length xs) (zs++ys) == elem (length xs) (ys++zs)"}}],[202.179352,{"FailedProof":{"prop_name":"elem (S x) (ys++xs) == elem (S x) (xs++ys)"}}],[204.198641,{"FailedProof":{"prop_name":"elem (x+x) (ys++xs) == elem (x+x) (xs++ys)"}}],[206.231823,{"FailedProof":{"prop_name":"elem (y+y) (drop y xs) == elem (y+y) (drop x xs)"}}],[208.250264,{"FailedProof":{"prop_name":"drop (S y) (drop x xs) == drop (S x) (drop y xs)"}}],[210.280988,{"FailedProof":{"prop_name":"elem Z (ys++xs) == elem Z (xs++ys)"}}],[211.294343,{"FailedProof":{"prop_name":"elem (length xs) (ys++xs) == elem (length xs) (xs++ys)"}}],[213.317553,{"FailedProof":{"prop_name":"elem (length ys) (ys++xs) == elem (length ys) (xs++ys)"}}],[214.321275,{"FailedProof":{"prop_name":"drop (x+x) (Z:xs) == drop (x+x) (x:xs)"}}],[215.336487,{"FailedProof":{"prop_name":"elem (S Z) (xs++xs) == elem (S Z) xs"}}],[217.34416,{"FailedProof":{"prop_name":"elem (y+z) (z:[]) == elem (x+y) (x:[])"}}],[219.35849,{"FailedProof":{"prop_name":"elem y (Z:[]) == elem (x+y) (x:[])"}}],[220.37931,{"FailedProof":{"prop_name":"elem Z (y:[]) == elem (x+y) (x:[])"}}],[222.393555,{"FailedProof":{"prop_name":"elem (y+y) (y:[]) == elem (x+y) (x:[])"}}],[223.399022,{"FailedProof":{"prop_name":"elem (y+y) (Z:[]) == elem (x+y) (x:[])"}}],[225.413239,{"FailedProof":{"prop_name":"elem x (Z:[]) == elem (x+y) (y:[])"}}],[226.420576,{"FailedProof":{"prop_name":"elem Z (x:[]) == elem (x+y) (y:[])"}}],[228.436933,{"FailedProof":{"prop_name":"elem (x+x) (x:[]) == elem (x+y) (y:[])"}}],[229.440097,{"FailedProof":{"prop_name":"elem (x+x) (Z:[]) == elem (x+y) (y:[])"}}],[231.505143,{"FailedProof":{"prop_name":"elem (y+z) (y:[]) == elem (x+z) (x:[])"}}],[233.467358,{"FailedProof":{"prop_name":"drop (x+y) (Z:[]) == drop (x+y) (x:[])"}}],[235.487664,{"FailedProof":{"prop_name":"elem (S Z) (ys++xs) == elem (S Z) (xs++ys)"}}],[237.510718,{"FailedProof":{"prop_name":"elem x (ys++xs) == elem x (xs++ys)"}}],[239.526497,{"FailedProof":{"prop_name":"drop y (drop x xs) == drop x (drop y xs)"}}],[241.548885,{"FailedProof":{"prop_name":"drop (x+y) xs == drop x (drop y xs)"}}],[243.55739,{"FailedProof":{"prop_name":"elem x (x:ys) == elem x (x:xs)"}}],[245.570416,{"FailedProof":{"prop_name":"elem x (xs++xs) == elem x xs"}}],[247.607403,{"FailedProof":{"prop_name":"elem y (y:xs) == elem x (x:xs)"}}],[249.660943,{"FailedProof":{"prop_name":"elem y (x:[]) == elem x (y:[])"}}],[251.693842,{"FailedProof":{"prop_name":"elem (x+z) (z:[]) == elem (x+y) (y:[])"}}],[253.706589,{"FailedProof":{"prop_name":"elem (x+x) (Z:xs) == elem (x+x) (x:xs)"}}],[254.722644,{"FailedProof":{"prop_name":"drop (length xs) (drop x xs) == []"}}],[255.744468,{"FailedProof":{"prop_name":"elem Z (xs++xs) == elem Z xs"}}],[257.791598,{"FailedProof":{"prop_name":"elem (x+y) (xs++xs) == elem (x+y) xs"}}],[259.894796,{"FailedProof":{"prop_name":"elem (x+z) (Z:xs) == elem (x+z) xs"}}],[263.073483,{"FailedProof":{"prop_name":"elem (y+z) (drop x zs) == elem (y+z) zs"}}],[266.115032,{"FailedProof":{"prop_name":"elem y (y:ys) == elem x (x:xs)"}}],[267.123136,{"FailedProof":{"prop_name":"elem x (x:[]) == elem x (x:xs)"}}],[269.158009,{"FailedProof":{"prop_name":"elem y (y:[]) == elem x (x:xs)"}}],[271.144433,{"FailedProof":{"prop_name":"elem Z (Z:xs) == elem x (x:xs)"}}],[273.162039,{"FailedProof":{"prop_name":"elem Z (Z:ys) == elem x (x:xs)"}}],[275.167165,{"FailedProof":{"prop_name":"elem Z (Z:[]) == elem x (x:xs)"}}],[277.184545,{"FailedProof":{"prop_name":"drop (x+x) xs == drop x (drop x xs)"}}],[278.197658,{"FailedProof":{"prop_name":"elem (length xs) (ys++ys) == elem (length xs) ys"}}],[280.211484,{"FailedProof":{"prop_name":"elem (S x) (xs++xs) == elem (S x) xs"}}],[281.224144,{"FailedProof":{"prop_name":"elem (x+x) (xs++xs) == elem (x+x) xs"}}],[283.238346,{"FailedProof":{"prop_name":"drop (S Z) (drop x xs) == drop (S x) xs"}}],[284.250774,{"FailedProof":{"prop_name":"elem (length xs) (xs++xs) == elem (length xs) xs"}}],[287.306953,{"FailedProof":{"prop_name":"elem (x+y) (ys++xs) == elem (x+y) (xs++ys)"}}],[289.417347,{"FailedProof":{"prop_name":"drop (x+z) (drop y xs) == drop (x+y) (drop z xs)"}}],[292.532271,{"FailedProof":{"prop_name":"drop (y+z) (drop x xs) == drop (x+y) (drop z xs)"}}],[294.54105,{"FailedProof":{"prop_name":"drop (x+y) (Z:xs) == drop (x+y) (x:xs)"}}],[296.678154,{"FailedProof":{"prop_name":"drop (x+x) (drop y xs) == drop (x+y) (drop x xs)"}}],[298.821795,{"FailedProof":{"prop_name":"drop (y+y) (drop x xs) == drop (x+y) (drop y xs)"}}],[300.86015,{"FailedProof":{"prop_name":"elem (length xs) (zs++ys) == elem (length xs) (ys++zs)"}}],[302.875875,{"FailedProof":{"prop_name":"elem (S x) (ys++xs) == elem (S x) (xs++ys)"}}],[304.90148,{"FailedProof":{"prop_name":"elem (x+x) (ys++xs) == elem (x+x) (xs++ys)"}}],[306.927476,{"FailedProof":{"prop_name":"elem (y+y) (drop y xs) == elem (y+y) (drop x xs)"}}],[308.951672,{"FailedProof":{"prop_name":"drop (S y) (drop x xs) == drop (S x) (drop y xs)"}}],[310.960318,{"FailedProof":{"prop_name":"elem Z (ys++xs) == elem Z (xs++ys)"}}],[312.981643,{"FailedProof":{"prop_name":"elem (length xs) (ys++xs) == elem (length xs) (xs++ys)"}}],[313.995466,{"FailedProof":{"prop_name":"elem (length ys) (ys++xs) == elem (length ys) (xs++ys)"}}],[316.008634,{"FailedProof":{"prop_name":"drop (x+x) (Z:xs) == drop (x+x) (x:xs)"}}],[317.020355,{"FailedProof":{"prop_name":"elem (S Z) (xs++xs) == elem (S Z) xs"}}],[319.038192,{"FailedProof":{"prop_name":"elem (y+z) (z:[]) == elem (x+y) (x:[])"}}],[321.046188,{"FailedProof":{"prop_name":"elem y (Z:[]) == elem (x+y) (x:[])"}}],[323.059736,{"FailedProof":{"prop_name":"elem Z (y:[]) == elem (x+y) (x:[])"}}],[324.065593,{"FailedProof":{"prop_name":"elem (y+y) (y:[]) == elem (x+y) (x:[])"}}],[326.079369,{"FailedProof":{"prop_name":"elem (y+y) (Z:[]) == elem (x+y) (x:[])"}}],[327.085674,{"FailedProof":{"prop_name":"elem x (Z:[]) == elem (x+y) (y:[])"}}],[329.10158,{"FailedProof":{"prop_name":"elem Z (x:[]) == elem (x+y) (y:[])"}}],[330.105925,{"FailedProof":{"prop_name":"elem (x+x) (x:[]) == elem (x+y) (y:[])"}}],[332.120615,{"FailedProof":{"prop_name":"elem (x+x) (Z:[]) == elem (x+y) (y:[])"}}],[334.161295,{"FailedProof":{"prop_name":"elem (y+z) (y:[]) == elem (x+z) (x:[])"}}],[336.181594,{"FailedProof":{"prop_name":"drop (x+y) (Z:[]) == drop (x+y) (x:[])"}}],[337.19418,{"FailedProof":{"prop_name":"elem (S Z) (ys++xs) == elem (S Z) (xs++ys)"}}],[337.194186,{"StartingUserLemmas":[]}],[337.233552,{"PlainProof":{"lemmas":[],"prop_name":"prop_T15"}}],[338.237451,{"InductiveProof":{"lemmas":[],"prop_name":"prop_T1"}}],[340.322389,{"FailedProof":{"prop_name":"prop_T9"}}],[342.342376,{"FailedProof":{"prop_name":"prop_T8"}}],[343.456505,{"InductiveProof":{"lemmas":[],"prop_name":"prop_T39"}}],[345.474866,{"InductiveProof":{"lemmas":[],"prop_name":"prop_T38"}}],[347.463018,{"InductiveProof":{"lemmas":[],"prop_name":"prop_T37"}}],[348.505489,{"PlainProof":{"lemmas":[],"prop_name":"prop_T24"}}],[349.232877,{"InductiveProof":{"lemmas":[],"prop_name":"prop_T36"}}],[349.282549,{"PlainProof":{"lemmas":[],"prop_name":"prop_T26"}}],[349.511728,{"InductiveProof":{"lemmas":[],"prop_name":"prop_T16"}}],[350.28839,{"InductiveProof":{"lemmas":[],"prop_name":"prop_T13"}}],[352.312798,{"FailedProof":{"prop_name":"prop_T47"}}],[354.324523,{"FailedProof":{"prop_name":"prop_T46"}}],[355.584127,{"FailedProof":{"prop_name":"prop_T45"}}],[357.603673,{"FailedProof":{"prop_name":"prop_T44"}}],[359.363327,{"FailedProof":{"prop_name":"prop_T50"}}],[360.632289,{"FailedProof":{"prop_name":"prop_T49"}}],[361.64518,{"FailedProof":{"prop_name":"prop_T48"}}],[361.734973,{"PlainProof":{"lemmas":[],"prop_name":"prop_T3"}}],[361.766291,{"PlainProof":{"lemmas":[],"prop_name":"prop_T25"}}],[361.797137,{"PlainProof":{"lemmas":[],"prop_name":"prop_T23"}}],[361.827878,{"PlainProof":{"lemmas":[],"prop_name":"prop_T22"}}],[362.389602,{"InductiveProof":{"lemmas":[],"prop_name":"prop_T4"}}],[362.473625,{"PlainProof":{"lemmas":[],"prop_name":"prop_T2"}}],[362.953219,{"InductiveProof":{"lemmas":[],"prop_name":"prop_T20"}}],[364.486821,{"FailedProof":{"prop_name":"prop_T34"}}],[365.983092,{"FailedProof":{"prop_name":"prop_T35"}}],[366.988596,{"FailedProof":{"prop_name":"prop_T33"}}],[368.517583,{"FailedProof":{"prop_name":"prop_T7"}}],[369.530727,{"FailedProof":{"prop_name":"prop_T31"}}],[371.024337,{"FailedProof":{"prop_name":"prop_T6"}}],[371.545041,{"InductiveProof":{"lemmas":[],"prop_name":"prop_T5"}}],[372.560433,{"FailedProof":{"prop_name":"prop_T30"}}],[373.573469,{"FailedProof":{"prop_name":"prop_T29"}}],[374.586191,{"FailedProof":{"prop_name":"prop_T27"}}],[376.09245,{"FailedProof":{"prop_name":"prop_T19"}}],[377.618576,{"FailedProof":{"prop_name":"prop_T17"}}],[378.63935,{"InductiveProof":{"lemmas":[],"prop_name":"prop_T12"}}],[379.652891,{"FailedProof":{"prop_name":"prop_T10"}}],[381.166111,{"FailedProof":{"prop_name":"prop_G6"}}],[382.18953,{"InductiveProof":{"lemmas":[],"prop_name":"prop_G5"}}],[383.202217,{"FailedProof":{"prop_name":"prop_T32"}}],[384.718183,{"FailedProof":{"prop_name":"prop_G9"}}],[386.509185,{"InductiveProof":{"lemmas":[],"prop_name":"prop_T43"}}],[388.521231,{"FailedProof":{"prop_name":"prop_T42"}}],[390.271227,{"FailedProof":{"prop_name":"prop_T41"}}],[391.277623,{"InductiveProof":{"lemmas":[],"prop_name":"prop_T40"}}],[392.290831,{"FailedProof":{"prop_name":"prop_T14"}}],[392.290927,{"Finished":{"unproved":["prop_T9","prop_T8","prop_T47","prop_T46","prop_T45","prop_T44","prop_T50","prop_T49","prop_T48","prop_T34","prop_T35","prop_T33","prop_T7","prop_T31","prop_T6","prop_T30","prop_T29","prop_T27","prop_T19","prop_T17","prop_T10","prop_G6","prop_T32","prop_G9","prop_T42","prop_T41","prop_T14"],"qs_proved":["xs++[] == xs","x+Z == x","(xs++ys)++zs == xs++(ys++zs)","x+S y == S (x+y)","drop (length xs) xs == []","drop (length xs) (xs++ys) == ys","length xs+length ys == length (xs++ys)","elem (S x) (x:[]) == elem x []","(x+y)+z == x+(y+z)","(y+z)+x == x+(y+z)"],"qs_unproved":["elem x (xs++ys) == elem x (ys++xs)","drop x (drop y xs) == drop y (drop x xs)","drop (x+y) xs == drop x (drop y xs)","elem x (x:xs) == elem x (x:ys)","elem x (xs++xs) == elem x xs","elem x (x:xs) == elem y (y:xs)","elem x (y:[]) == elem y (x:[])","elem (x+y) (y:[]) == elem (x+z) (z:[])","elem (x+x) (Z:xs) == elem (x+x) (x:xs)","drop (length xs) (drop x xs) == []","elem Z (xs++xs) == elem Z xs","elem (x+y) (xs++xs) == elem (x+y) xs","elem (x+y) (Z:xs) == elem (x+y) xs","elem (x+y) (drop z xs) == elem (x+y) xs","elem x (x:xs) == elem y (y:ys)","elem x (x:[]) == elem x (x:xs)","elem x (x:[]) == elem y (y:xs)","elem Z (Z:xs) == elem x (x:xs)","elem Z (Z:xs) == elem x (x:ys)","elem Z (Z:[]) == elem x (x:xs)","drop (x+x) xs == drop x (drop x xs)","elem (length xs) (ys++ys) == elem (length xs) ys","elem (S x) (xs++xs) == elem (S x) xs","elem (x+x) (xs++xs) == elem (x+x) xs","drop (S Z) (drop x xs) == drop (S x) xs","elem (length xs) (xs++xs) == elem (length xs) xs","elem (x+y) (xs++ys) == elem (x+y) (ys++xs)","drop (x+y) (drop z xs) == drop (x+z) (drop y xs)","drop (x+y) (drop z xs) == drop (z+x) (drop y xs)","drop (x+y) (Z:xs) == drop (x+y) (x:xs)","drop (x+x) (drop y xs) == drop (x+y) (drop x xs)","drop (x+x) (drop y xs) == drop (y+x) (drop x xs)","elem (length xs) (ys++zs) == elem (length xs) (zs++ys)","elem (S x) (xs++ys) == elem (S x) (ys++xs)","elem (x+x) (xs++ys) == elem (x+x) (ys++xs)","elem (x+x) (drop x xs) == elem (x+x) (drop y xs)","drop (S x) (drop y xs) == drop (S y) (drop x xs)","elem Z (xs++ys) == elem Z (ys++xs)","elem (length xs) (ys++xs) == elem (length xs) (xs++ys)","elem (length xs) (xs++ys) == elem (length xs) (ys++xs)","drop (x+x) (Z:xs) == drop (x+x) (x:xs)","elem (S Z) (xs++xs) == elem (S Z) xs","elem (x+y) (y:[]) == elem (z+x) (z:[])","elem x (Z:[]) == elem (y+x) (y:[])","elem Z (x:[]) == elem (y+x) (y:[])","elem (x+x) (x:[]) == elem (y+x) (y:[])","elem (x+x) (Z:[]) == elem (y+x) (y:[])","elem x (Z:[]) == elem (x+y) (y:[])","elem Z (x:[]) == elem (x+y) (y:[])","elem (x+x) (x:[]) == elem (x+y) (y:[])","elem (x+x) (Z:[]) == elem (x+y) (y:[])","elem (x+y) (x:[]) == elem (z+y) (z:[])","drop (x+y) (Z:[]) == drop (x+y) (x:[])","elem (S Z) (xs++ys) == elem (S Z) (ys++xs)"],"proved":["prop_T1","prop_T39","prop_T38","prop_T37","prop_T36","prop_T16","prop_T13","prop_T4","prop_T20","prop_T5","prop_T12","prop_G5","prop_T43","prop_T40","prop_T15","prop_T24","prop_T26","prop_T3","prop_T25","prop_T23","prop_T22","prop_T2"]}}]]