[[3.0e-6,{"Started":[]}],[1.565006,{"FileProcessed":[]}],[2.612726,{"QuickSpecDone":{"classes":2762,"eqs":1004}}],[5.736523,{"InductiveProof":{"lemmas":[],"prop_name":"y+x == x+y"}}],[5.838297,{"InductiveProof":{"lemmas":[],"prop_name":"xs++[] == xs"}}],[5.871864,{"PlainProof":{"lemmas":[],"prop_name":"elem y [] == elem x []"}}],[5.87955,{"PlainProof":{"lemmas":[],"prop_name":"drop x [] == []"}}],[5.889723,{"PlainProof":{"lemmas":[],"prop_name":"x+Z == x"}}],[5.895303,{"PlainProof":{"lemmas":[],"prop_name":"[]++xs == xs"}}],[5.920664,{"PlainProof":{"lemmas":[],"prop_name":"drop Z xs == xs"}}],[5.921519,{"PlainProof":{"lemmas":[],"prop_name":"length [] == Z"}}],[10.032808,{"FailedProof":{"prop_name":"elem x (ys++xs) == elem x (xs++ys)"}}],[13.9867,{"InductiveProof":{"lemmas":[],"prop_name":"drop y (drop x xs) == drop x (drop y xs)"}}],[15.006303,{"InductiveProof":{"lemmas":[],"prop_name":"y+(x+z) == x+(y+z)"}}],[17.043259,{"InductiveProof":{"lemmas":[],"prop_name":"(xs++ys)++zs == xs++(ys++zs)"}}],[17.087374,{"PlainProof":{"lemmas":[],"prop_name":"(x:xs)++ys == x:(xs++ys)"}}],[18.800868,{"InductiveProof":{"lemmas":[],"prop_name":"drop (x+y) xs == drop x (drop y xs)"}}],[20.863105,{"PlainProof":{"lemmas":[],"prop_name":"length (y:xs) == length (x:xs)"}}],[20.866082,{"FailedProof":{"prop_name":"length (ys++xs) == length (xs++ys)"}}],[24.906544,{"FailedProof":{"prop_name":"elem x (x:ys) == elem x (x:xs)"}}],[26.927968,{"FailedProof":{"prop_name":"elem x (xs++xs) == elem x xs"}}],[31.082466,{"PlainProof":{"lemmas":[],"prop_name":"x+S y == S (x+y)"}}],[31.158803,{"FailedProof":{"prop_name":"elem y (y:xs) == elem x (x:xs)"}}],[31.177481,{"PlainProof":{"lemmas":[],"prop_name":"S (length xs) == length (x:xs)"}}],[32.176769,{"InductiveProof":{"lemmas":[],"prop_name":"drop (length xs) xs == []"}}],[35.279243,{"PlainProof":{"lemmas":[],"prop_name":"drop (S x) (y:xs) == drop x xs"}}],[35.28801,{"InductiveProof":{"lemmas":[],"prop_name":"drop (x+y) (y:xs) == drop (x+y) (x:xs)"}}],[37.325071,{"FailedProof":{"prop_name":"elem y (x:[]) == elem x (y:[])"}}],[39.341269,{"FailedProof":{"prop_name":"elem (S x) (x:xs) == elem (S x) xs"}}],[40.378453,{"InductiveProof":{"lemmas":[],"prop_name":"drop (length xs) (xs++ys) == ys"}}],[42.416851,{"InductiveProof":{"lemmas":[],"prop_name":"length xs+length ys == length (xs++ys)"}}],[46.605171,{"FailedProof":{"prop_name":"elem (x+z) (z:[]) == elem (x+y) (y:[])"}}],[46.623548,{"PlainProof":{"lemmas":[],"prop_name":"elem (S x) (Z:xs) == elem (S x) xs"}}],[48.650765,{"FailedProof":{"prop_name":"elem (x+x) (Z:xs) == elem (x+x) (x:xs)"}}],[48.673313,{"PlainProof":{"lemmas":[],"prop_name":"drop (x+x) (y:[]) == drop x (y:[])"}}],[48.701408,{"Discard":{"discarded":["xs++[] == xs","[]++xs == xs","drop Z xs == xs","drop (length xs) (xs++ys) == ys","drop (length xs) (xs++ys) == ys","drop (length xs) (xs++xs) == xs","drop (S Z) (x:xs) == xs","drop (S Z) (x:xs) == xs","drop (S Z) (x:xs) == xs","drop (S Z) (Z:xs) == xs","xs++[] == xs","[]++xs == xs","drop Z xs == xs","drop (length xs) (xs++ys) == ys","drop (length xs) (xs++ys) == ys","drop (length xs) (xs++xs) == xs","drop (S Z) (x:xs) == xs","drop (S Z) (x:xs) == xs","drop (S Z) (x:xs) == xs","drop (S Z) (Z:xs) == xs","xs++[] == xs","[]++xs == xs","drop Z xs == xs","drop (length xs) (xs++ys) == ys","drop (length xs) (xs++ys) == ys","drop (length xs) (xs++xs) == xs","drop (S Z) (x:xs) == xs","drop (S Z) (x:xs) == xs","drop (S Z) (x:xs) == xs","drop (S Z) (Z:xs) == xs","x+Z == x","Z+x == x","x+Z == x","Z+x == x","x+Z == x","Z+x == x","drop x [] == []","drop x [] == []","drop x [] == []","[]++[] == []","drop Z [] == []","drop (length xs) xs == []","drop (length xs) xs == []","drop (length xs) xs == []","drop (x+y) [] == []","drop (x+y) [] == []","drop (x+y) [] == []","drop (length xs) (drop x xs) == []","drop (length xs) (drop x xs) == []","drop (length xs) (drop x xs) == []","drop (length xs) (drop x xs) == []","drop (length xs) (drop x xs) == []","drop (length xs) (drop x xs) == []","drop (length xs) (drop x xs) == []","drop (length xs) (drop x xs) == []","drop (length xs) (drop x xs) == []","drop (length xs) [] == []","drop (length xs) [] == []","drop (length xs) [] == []","drop (S x) [] == []","drop (S x) [] == []","drop (S x) [] == []","drop (x+x) [] == []","drop (x+x) [] == []","drop (x+x) [] == []","drop (S x) (y:[]) == []","drop (S x) (y:[]) == []","drop (S x) (y:[]) == []","drop (S x) (y:[]) == []","drop (S x) (y:[]) == []","drop (S x) (y:[]) == []","drop (S x) (x:[]) == []","drop (S x) (x:[]) == []","drop (S x) (x:[]) == []","drop (S Z) [] == []","drop (S x) (Z:[]) == []","drop (S x) (Z:[]) == []","drop (S x) (Z:[]) == []","drop (S Z) (x:[]) == []","drop (S Z) (x:[]) == []","drop (S Z) (x:[]) == []","drop (S Z) (Z:[]) == []","length [] == Z","Z+Z == Z","[]++(xs++ys) == xs++ys","drop Z (xs++ys) == xs++ys","(xs++ys)++[] == xs++ys","[]++(xs++ys) == xs++ys","drop Z (xs++ys) == xs++ys","(xs++ys)++[] == xs++ys","[]++(xs++ys) == xs++ys","drop Z (xs++ys) == xs++ys","(xs++ys)++[] == xs++ys","[]++(xs++ys) == xs++ys","drop Z (xs++ys) == xs++ys","(xs++ys)++[] == xs++ys","[]++(xs++ys) == xs++ys","drop Z (xs++ys) == xs++ys","(xs++ys)++[] == xs++ys","[]++(xs++ys) == xs++ys","drop Z (xs++ys) == xs++ys","(xs++ys)++[] == xs++ys","elem x (xs++xs) == elem x xs","elem x (xs++xs) == elem x xs","elem x (xs++xs) == elem x xs","elem x (xs++xs) == elem x xs","elem x (xs++xs) == elem x xs","elem x (xs++xs) == elem x xs","elem x (xs++xs) == elem x xs","elem x (xs++xs) == elem x xs","elem x (xs++xs) == elem x xs","[]++(x:xs) == x:xs","drop Z (x:xs) == x:xs","(x:xs)++[] == x:xs","(x:[])++xs == x:xs","[]++(x:xs) == x:xs","drop Z (x:xs) == x:xs","(x:xs)++[] == x:xs","(x:[])++xs == x:xs","[]++(x:xs) == x:xs","drop Z (x:xs) == x:xs","(x:xs)++[] == x:xs","(x:[])++xs == x:xs","[]++(x:xs) == x:xs","drop Z (x:xs) == x:xs","(x:xs)++[] == x:xs","(x:[])++xs == x:xs","[]++(x:xs) == x:xs","drop Z (x:xs) == x:xs","(x:xs)++[] == x:xs","(x:[])++xs == x:xs","[]++(x:xs) == x:xs","drop Z (x:xs) == x:xs","(x:xs)++[] == x:xs","(x:[])++xs == x:xs","[]++(x:xs) == x:xs","drop Z (x:xs) == x:xs","(x:xs)++[] == x:xs","(x:[])++xs == x:xs","[]++(x:xs) == x:xs","drop Z (x:xs) == x:xs","(x:xs)++[] == x:xs","(x:[])++xs == x:xs","[]++(x:xs) == x:xs","drop Z (x:xs) == x:xs","(x:xs)++[] == x:xs","(x:[])++xs == x:xs","drop (S x) (y:xs) == drop x xs","drop (S x) (y:xs) == drop x xs","[]++drop x xs == drop x xs","drop Z (drop x xs) == drop x xs","drop x xs++[] == drop x xs","drop (S x) (x:xs) == drop x xs","drop (S x) (Z:xs) == drop x xs","drop (S x) (y:xs) == drop x xs","drop (S x) (y:xs) == drop x xs","[]++drop x xs == drop x xs","drop Z (drop x xs) == drop x xs","drop x xs++[] == drop x xs","drop (S x) (x:xs) == drop x xs","drop (S x) (Z:xs) == drop x xs","drop (S x) (y:xs) == drop x xs","drop (S x) (y:xs) == drop x xs","[]++drop x xs == drop x xs","drop Z (drop x xs) == drop x xs","drop x xs++[] == drop x xs","drop (S x) (x:xs) == drop x xs","drop (S x) (Z:xs) == drop x xs","drop (S x) (y:xs) == drop x xs","drop (S x) (y:xs) == drop x xs","[]++drop x xs == drop x xs","drop Z (drop x xs) == drop x xs","drop x xs++[] == drop x xs","drop (S x) (x:xs) == drop x xs","drop (S x) (Z:xs) == drop x xs","drop (S x) (y:xs) == drop x xs","drop (S x) (y:xs) == drop x xs","[]++drop x xs == drop x xs","drop Z (drop x xs) == drop x xs","drop x xs++[] == drop x xs","drop (S x) (x:xs) == drop x xs","drop (S x) (Z:xs) == drop x xs","drop (S x) (y:xs) == drop x xs","drop (S x) (y:xs) == drop x xs","[]++drop x xs == drop x xs","drop Z (drop x xs) == drop x xs","drop x xs++[] == drop x xs","drop (S x) (x:xs) == drop x xs","drop (S x) (Z:xs) == drop x xs","drop (S x) (y:xs) == drop x xs","drop (S x) (y:xs) == drop x xs","[]++drop x xs == drop x xs","drop Z (drop x xs) == drop x xs","drop x xs++[] == drop x xs","drop (S x) (x:xs) == drop x xs","drop (S x) (Z:xs) == drop x xs","drop (S x) (y:xs) == drop x xs","drop (S x) (y:xs) == drop x xs","[]++drop x xs == drop x xs","drop Z (drop x xs) == drop x xs","drop x xs++[] == drop x xs","drop (S x) (x:xs) == drop x xs","drop (S x) (Z:xs) == drop x xs","drop (S x) (y:xs) == drop x xs","drop (S x) (y:xs) == drop x xs","[]++drop x xs == drop x xs","drop Z (drop x xs) == drop x xs","drop x xs++[] == drop x xs","drop (S x) (x:xs) == drop x xs","drop (S x) (Z:xs) == drop x xs","x+y == y+x","Z+(x+y) == x+y","(x+y)+Z == x+y","x+y == y+x","Z+(x+y) == x+y","(x+y)+Z == x+y","x+y == y+x","Z+(x+y) == x+y","(x+y)+Z == x+y","Z+length xs == length xs","length xs+Z == length xs","Z+length xs == length xs","length xs+Z == length xs","Z+length xs == length xs","length xs+Z == length xs","x+S Z == S x","Z+S x == S x","S x+Z == S x","S Z+x == S x","x+S Z == S x","Z+S x == S x","S x+Z == S x","S Z+x == S x","x+S Z == S x","Z+S x == S x","S x+Z == S x","S Z+x == S x","[]++(xs++xs) == xs++xs","drop Z (xs++xs) == xs++xs","(xs++xs)++[] == xs++xs","[]++(xs++xs) == xs++xs","drop Z (xs++xs) == xs++xs","(xs++xs)++[] == xs++xs","[]++(xs++xs) == xs++xs","drop Z (xs++xs) == xs++xs","(xs++xs)++[] == xs++xs","Z+(x+x) == x+x","(x+x)+Z == x+x","Z+(x+x) == x+x","(x+x)+Z == x+x","Z+(x+x) == x+x","(x+x)+Z == x+x","elem x [] == elem y []","elem x [] == elem y []","elem Z [] == elem x []","elem (x+y) [] == elem x []","elem (x+y) [] == elem x []","elem (x+y) [] == elem z []","elem (length xs) [] == elem x []","elem (length xs) [] == elem x []","elem (length xs) [] == elem x []","elem (S x) [] == elem x []","elem (S x) [] == elem y []","elem (S x) [] == elem y []","elem (x+x) [] == elem x []","elem (x+x) [] == elem y []","elem (x+x) [] == elem y []"]}}],[49.72349,{"FailedProof":{"prop_name":"elem (S x) (x:[]) == elem x []"}}],[51.765437,{"FailedProof":{"prop_name":"elem (S y) (y:[]) == elem x []"}}],[51.765508,{"Discard":{"discarded":["elem (S x) (x:[]) == elem y []","elem (S Z) [] == elem x []","elem (S x) (Z:[]) == elem x []","elem (S x) (Z:[]) == elem y []","elem (S x) (Z:[]) == elem y []","elem (S Z) (Z:[]) == elem x []","[]++(x:[]) == x:[]","drop Z (x:[]) == x:[]","(x:[])++[] == x:[]","[]++(x:[]) == x:[]","drop Z (x:[]) == x:[]","(x:[])++[] == x:[]","[]++(x:[]) == x:[]","drop Z (x:[]) == x:[]","(x:[])++[] == x:[]","elem Z (xs++xs) == elem Z xs","elem Z (xs++xs) == elem Z xs","[]++(Z:xs) == Z:xs","drop Z (Z:xs) == Z:xs","(Z:xs)++[] == Z:xs","(Z:[])++xs == Z:xs","[]++(Z:xs) == Z:xs","drop Z (Z:xs) == Z:xs","(Z:xs)++[] == Z:xs","(Z:[])++xs == Z:xs","[]++(Z:xs) == Z:xs","drop Z (Z:xs) == Z:xs","(Z:xs)++[] == Z:xs","(Z:[])++xs == Z:xs","length (x:[]) == S Z","length (x:[]) == S Z","length (x:[]) == S Z","length (Z:[]) == S Z","Z+S Z == S Z","S Z+Z == S Z","[]++(Z:[]) == Z:[]","drop Z (Z:[]) == Z:[]","(Z:[])++[] == Z:[]","(xs++ys)++zs == xs++(ys++zs)","(xs++ys)++zs == xs++(ys++zs)","(xs++ys)++zs == xs++(ys++zs)","(xs++ys)++zs == xs++(ys++zs)","(xs++ys)++zs == xs++(ys++zs)","(xs++ys)++zs == xs++(ys++zs)","elem x (xs++ys) == elem x (ys++xs)","elem x (xs++ys) == elem x (ys++xs)","elem x (xs++ys) == elem x (ys++xs)","elem x (xs++ys) == elem x (ys++xs)","elem x (xs++ys) == elem x (ys++xs)","elem x (xs++ys) == elem x (ys++xs)","elem x (xs++ys) == elem x (ys++xs)","elem x (xs++ys) == elem x (ys++xs)","elem x (xs++ys) == elem x (ys++xs)","(x:xs)++ys == x:(xs++ys)","(x:[])++(xs++ys) == x:(xs++ys)","(x:xs)++ys == x:(xs++ys)","(x:[])++(xs++ys) == x:(xs++ys)","(x:xs)++ys == x:(xs++ys)","(x:[])++(xs++ys) == x:(xs++ys)","(x:xs)++ys == x:(xs++ys)","(x:[])++(xs++ys) == x:(xs++ys)","(x:xs)++ys == x:(xs++ys)","(x:[])++(xs++ys) == x:(xs++ys)","(x:xs)++ys == x:(xs++ys)","(x:[])++(xs++ys) == x:(xs++ys)","(x:[])++(y:xs) == x:(y:xs)","(x:[])++(y:xs) == x:(y:xs)","(x:[])++(y:xs) == x:(y:xs)","(x:[])++(y:xs) == x:(y:xs)","(x:[])++(y:xs) == x:(y:xs)","(x:[])++(y:xs) == x:(y:xs)","(x:[])++drop y xs == x:drop y xs","(x:[])++drop y xs == x:drop y xs","(x:[])++drop y xs == x:drop y xs","(x:[])++drop y xs == x:drop y xs","(x:[])++drop y xs == x:drop y xs","(x:[])++drop y xs == x:drop y xs","(x:xs)++ys == x:(xs++ys)","(x:[])++(xs++ys) == x:(xs++ys)","(x:xs)++ys == x:(xs++ys)","(x:[])++(xs++ys) == x:(xs++ys)","(x:xs)++ys == x:(xs++ys)","(x:[])++(xs++ys) == x:(xs++ys)","(x:xs)++ys == x:(xs++ys)","(x:[])++(xs++ys) == x:(xs++ys)","(x:xs)++ys == x:(xs++ys)","(x:[])++(xs++ys) == x:(xs++ys)","(x:xs)++ys == x:(xs++ys)","(x:[])++(xs++ys) == x:(xs++ys)","(x:[])++(y:xs) == x:(y:xs)","(x:[])++(y:xs) == x:(y:xs)","(x:[])++(y:xs) == x:(y:xs)","(x:[])++(y:xs) == x:(y:xs)","(x:[])++(y:xs) == x:(y:xs)","(x:[])++(y:xs) == x:(y:xs)","(x:[])++drop y xs == x:drop y xs","(x:[])++drop y xs == x:drop y xs","(x:[])++drop y xs == x:drop y xs","(x:[])++drop y xs == x:drop y xs","(x:[])++drop y xs == x:drop y xs","(x:[])++drop y xs == x:drop y xs","(x:xs)++ys == x:(xs++ys)","(x:[])++(xs++ys) == x:(xs++ys)","(x:xs)++ys == x:(xs++ys)","(x:[])++(xs++ys) == x:(xs++ys)","(x:xs)++ys == x:(xs++ys)","(x:[])++(xs++ys) == x:(xs++ys)","(x:xs)++ys == x:(xs++ys)","(x:[])++(xs++ys) == x:(xs++ys)","(x:xs)++ys == x:(xs++ys)","(x:[])++(xs++ys) == x:(xs++ys)","(x:xs)++ys == x:(xs++ys)","(x:[])++(xs++ys) == x:(xs++ys)","(x:[])++(y:xs) == x:(y:xs)","(x:[])++(y:xs) == x:(y:xs)","(x:[])++(y:xs) == x:(y:xs)","(x:[])++(y:xs) == x:(y:xs)","(x:[])++(y:xs) == x:(y:xs)","(x:[])++(y:xs) == x:(y:xs)","(x:[])++drop y xs == x:drop y xs","(x:[])++drop y xs == x:drop y xs","(x:[])++drop y xs == x:drop y xs","(x:[])++drop y xs == x:drop y xs","(x:[])++drop y xs == x:drop y xs","(x:[])++drop y xs == x:drop y xs","drop x (drop y xs) == drop y (drop x xs)","drop (x+y) xs == drop x (drop y xs)","drop x (drop y xs) == drop y (drop x xs)","drop (x+y) xs == drop x (drop y xs)","drop x (drop y xs) == drop y (drop x xs)","drop (x+y) xs == drop x (drop y xs)","drop x (drop y xs) == drop y (drop x xs)","drop (x+y) xs == drop x (drop y xs)","drop x (drop y xs) == drop y (drop x xs)","drop (x+y) xs == drop x (drop y xs)","drop x (drop y xs) == drop y (drop x xs)","drop (x+y) xs == drop x (drop y xs)","drop x (drop y xs) == drop y (drop x xs)","drop (x+y) xs == drop x (drop y xs)","drop x (drop y xs) == drop y (drop x xs)","drop (x+y) xs == drop x (drop y xs)","drop x (drop y xs) == drop y (drop x xs)","drop (x+y) xs == drop x (drop y xs)","x+(y+z) == y+(x+z)","x+(y+z) == y+(z+x)","(x+y)+z == x+(y+z)","(x+y)+z == x+(z+y)","(x+y)+z == z+(x+y)"]}}],[52.789338,{"FailedProof":{"prop_name":"elem Z (xs++xs) == elem Z xs"}}],[56.837494,{"FailedProof":{"prop_name":"elem (x+y) (xs++xs) == elem (x+y) xs"}}],[56.837996,{"Discard":{"discarded":["elem (x+y) (xs++xs) == elem (x+y) xs","elem (x+y) (xs++xs) == elem (x+y) xs","elem (x+y) (xs++xs) == elem (x+y) xs","elem (x+y) (xs++xs) == elem (x+y) xs","elem (x+y) (xs++xs) == elem (x+y) xs","elem (x+y) (xs++xs) == elem (x+y) xs","elem (x+y) (xs++xs) == elem (x+y) xs","elem (x+y) (Z:xs) == elem (x+y) xs","elem (x+y) (xs++xs) == elem (x+y) xs","elem (x+y) (Z:xs) == elem (x+y) xs","length (xs++ys) == length (ys++xs)","length xs+length ys == length (xs++ys)","length xs+length ys == length (ys++xs)","length (xs++ys) == length (ys++xs)","length xs+length ys == length (xs++ys)","length xs+length ys == length (ys++xs)","length (xs++ys) == length (ys++xs)","length xs+length ys == length (xs++ys)","length xs+length ys == length (ys++xs)","length (x:xs) == length (y:xs)","length (x:xs) == length (y:xs)","S (length xs) == length (x:xs)","length (Z:xs) == length (x:xs)","length xs+S Z == length (x:xs)","S Z+length xs == length (x:xs)","length (x:xs) == length (y:xs)","length (x:xs) == length (y:xs)","S (length xs) == length (x:xs)","length (Z:xs) == length (x:xs)","length xs+S Z == length (x:xs)","S Z+length xs == length (x:xs)","length (x:xs) == length (y:xs)","length (x:xs) == length (y:xs)","S (length xs) == length (x:xs)","length (Z:xs) == length (x:xs)","length xs+S Z == length (x:xs)","S Z+length xs == length (x:xs)","x+S y == S (x+y)","x+S y == S (y+x)","S x+y == S (x+y)","S x+y == S (y+x)","(x+y)+S Z == S (x+y)","S Z+(x+y) == S (x+y)","x+S y == S (x+y)","x+S y == S (y+x)","S x+y == S (x+y)","S x+y == S (y+x)","(x+y)+S Z == S (x+y)","S Z+(x+y) == S (x+y)","x+S y == S (x+y)","x+S y == S (y+x)","S x+y == S (x+y)","S x+y == S (y+x)","(x+y)+S Z == S (x+y)","S Z+(x+y) == S (x+y)","(xs++xs)++ys == xs++(xs++ys)","(xs++xs)++ys == xs++(xs++ys)","(xs++ys)++xs == xs++(ys++xs)","(xs++ys)++xs == xs++(ys++xs)","(xs++ys)++ys == xs++(ys++ys)","(xs++ys)++ys == xs++(ys++ys)","(xs++ys)++xs == xs++(ys++xs)","(xs++xs)++ys == xs++(xs++ys)","(xs++xs)++ys == xs++(xs++ys)","(xs++ys)++xs == xs++(ys++xs)","(xs++ys)++ys == xs++(ys++ys)","(xs++ys)++ys == xs++(ys++ys)","(xs++ys)++xs == xs++(ys++xs)","(xs++ys)++xs == xs++(ys++xs)","(xs++xs)++ys == xs++(xs++ys)","(xs++xs)++ys == xs++(xs++ys)","(xs++ys)++ys == xs++(ys++ys)","(xs++ys)++ys == xs++(ys++ys)","elem x (x:xs) == elem x (x:ys)","elem x (x:xs) == elem x (x:ys)","elem x (x:xs) == elem y (y:xs)"]}}],[60.901434,{"FailedProof":{"prop_name":"elem (y+z) (Z:xs) == elem (y+z) xs"}}],[69.179178,{"FailedProof":{"prop_name":"elem y (y:ys) == elem x (x:xs)"}}],[69.179283,{"Discard":{"discarded":["elem x (x:xs) == elem y (y:ys)","elem x (x:xs) == elem y (y:xs)","elem x (x:xs) == elem y (y:ys)","elem x (x:xs) == elem y (y:ys)"]}}],[71.29534,{"FailedProof":{"prop_name":"elem x (x:[]) == elem x (x:xs)"}}],[75.466036,{"FailedProof":{"prop_name":"elem y (y:[]) == elem x (x:xs)"}}],[75.466116,{"Discard":{"discarded":["elem x (x:[]) == elem y (y:xs)"]}}],[77.521225,{"FailedProof":{"prop_name":"elem Z (Z:xs) == elem x (x:xs)"}}],[81.541397,{"FailedProof":{"prop_name":"elem Z (Z:ys) == elem x (x:xs)"}}],[81.541814,{"Discard":{"discarded":["elem Z (Z:xs) == elem x (x:ys)","(x:[])++(x:xs) == x:(x:xs)","(x:[])++(x:xs) == x:(x:xs)","(x:[])++(x:xs) == x:(x:xs)","(x:[])++drop x xs == x:drop x xs","(x:[])++drop x xs == x:drop x xs","(x:[])++drop x xs == x:drop x xs","(x:xs)++xs == x:(xs++xs)","(x:[])++(xs++xs) == x:(xs++xs)","(x:xs)++xs == x:(xs++xs)","(x:[])++(xs++xs) == x:(xs++xs)","(x:xs)++xs == x:(xs++xs)","(x:[])++(xs++xs) == x:(xs++xs)","(x:[])++(x:xs) == x:(x:xs)","(x:[])++(x:xs) == x:(x:xs)","(x:[])++(x:xs) == x:(x:xs)","(x:[])++drop x xs == x:drop x xs","(x:[])++drop x xs == x:drop x xs","(x:[])++drop x xs == x:drop x xs","(x:xs)++xs == x:(xs++xs)","(x:[])++(xs++xs) == x:(xs++xs)","(x:xs)++xs == x:(xs++xs)","(x:[])++(xs++xs) == x:(xs++xs)","(x:xs)++xs == x:(xs++xs)","(x:[])++(xs++xs) == x:(xs++xs)","(x:[])++(x:xs) == x:(x:xs)","(x:[])++(x:xs) == x:(x:xs)","(x:[])++(x:xs) == x:(x:xs)","(x:[])++drop x xs == x:drop x xs","(x:[])++drop x xs == x:drop x xs","(x:[])++drop x xs == x:drop x xs","(x:xs)++xs == x:(xs++xs)","(x:[])++(xs++xs) == x:(xs++xs)","(x:xs)++xs == x:(xs++xs)","(x:[])++(xs++xs) == x:(xs++xs)","(x:xs)++xs == x:(xs++xs)","(x:[])++(xs++xs) == x:(xs++xs)","drop x (Z:xs) == drop x (x:xs)","drop x (Z:xs) == drop x (x:xs)","drop x (Z:xs) == drop x (x:xs)","drop (x+x) xs == drop x (drop x xs)","drop (x+x) xs == drop x (drop x xs)","drop (x+x) xs == drop x (drop x xs)","drop x (Z:xs) == drop x (x:xs)","drop x (Z:xs) == drop x (x:xs)","drop x (Z:xs) == drop x (x:xs)","drop (x+x) xs == drop x (drop x xs)","drop (x+x) xs == drop x (drop x xs)","drop (x+x) xs == drop x (drop x xs)","drop x (Z:xs) == drop x (x:xs)","drop x (Z:xs) == drop x (x:xs)","drop x (Z:xs) == drop x (x:xs)","drop (x+x) xs == drop x (drop x xs)","drop (x+x) xs == drop x (drop x xs)","drop (x+x) xs == drop x (drop x xs)","x+(y+y) == y+(y+x)","(x+y)+x == x+(x+y)","(x+x)+y == x+(x+y)","x+(y+y) == y+(y+x)","(x+y)+x == x+(x+y)","(x+x)+y == x+(x+y)","length xs+x == x+length xs","length xs+x == x+length xs","length xs+x == x+length xs","x+(y+x) == y+(x+x)","(x+y)+y == x+(y+y)","(x+x)+y == y+(x+x)","x+(y+x) == y+(x+x)","(x+y)+y == x+(y+y)","(x+x)+y == y+(x+x)","x+(y+y) == y+(y+x)","(x+y)+x == x+(x+y)","(x+x)+y == x+(x+y)","length xs+x == x+length xs","length xs+x == x+length xs","length xs+x == x+length xs","x+(y+x) == y+(x+x)","(x+y)+y == x+(y+y)","(x+x)+y == y+(x+x)","length xs+x == x+length xs","length xs+x == x+length xs","length xs+x == x+length xs"]}}],[83.569333,{"FailedProof":{"prop_name":"elem Z (Z:[]) == elem x (x:xs)"}}],[85.598387,{"FailedProof":{"prop_name":"elem (length xs) (ys++ys) == elem (length xs) ys"}}],[85.598456,{"Discard":{"discarded":["elem (length xs) (ys++ys) == elem (length xs) ys","elem (length xs) (ys++ys) == elem (length xs) ys","elem (length xs) (ys++ys) == elem (length xs) ys","elem (length xs) (ys++ys) == elem (length xs) ys","elem (length xs) (ys++ys) == elem (length xs) ys","elem (S x) (x:xs) == elem (S x) xs","elem (S x) (Z:xs) == elem (S x) xs","elem (S x) (x:xs) == elem (S x) xs","elem (S x) (xs++xs) == elem (S x) xs","elem (S x) (Z:xs) == elem (S x) xs","elem (S x) (x:xs) == elem (S x) xs","elem (S x) (xs++xs) == elem (S x) xs","elem (S x) (Z:xs) == elem (S x) xs","elem (S x) (x:xs) == elem (S x) xs","elem (S x) (xs++xs) == elem (S x) xs","elem (S x) (Z:xs) == elem (S x) xs","elem (S x) (x:xs) == elem (S x) xs","elem (S x) (xs++xs) == elem (S x) xs","elem (S x) (Z:xs) == elem (S x) xs","elem (S x) (x:xs) == elem (S x) xs","elem (S x) (xs++xs) == elem (S x) xs","elem (S x) (Z:xs) == elem (S x) xs","elem (S x) (x:xs) == elem (S x) xs","elem (S x) (xs++xs) == elem (S x) xs","elem (S x) (Z:xs) == elem (S x) xs","elem (S x) (x:xs) == elem (S x) xs","elem (S x) (xs++xs) == elem (S x) xs","elem (S x) (Z:xs) == elem (S x) xs","elem (S x) (x:xs) == elem (S x) xs","elem (S x) (xs++xs) == elem (S x) xs","elem (S x) (Z:xs) == elem (S x) xs"]}}],[87.627502,{"FailedProof":{"prop_name":"elem (S x) (xs++xs) == elem (S x) xs"}}],[89.65018,{"FailedProof":{"prop_name":"elem (x+x) (xs++xs) == elem (x+x) xs"}}],[89.650257,{"Discard":{"discarded":["elem (x+x) (xs++xs) == elem (x+x) xs","elem (x+x) (xs++xs) == elem (x+x) xs","elem (x+x) (xs++xs) == elem (x+x) xs","elem (x+x) (xs++xs) == elem (x+x) xs","elem (x+x) (xs++xs) == elem (x+x) xs","elem (x+x) (xs++xs) == elem (x+x) xs","elem (x+x) (xs++xs) == elem (x+x) xs","elem (x+x) (xs++xs) == elem (x+x) xs","drop (S Z) (drop x xs) == drop (S x) xs","drop (S Z) (drop x xs) == drop (S x) xs","drop (S Z) (drop x xs) == drop (S x) xs","drop (S Z) (drop x xs) == drop (S x) xs","drop (S Z) (drop x xs) == drop (S x) xs","drop (S Z) (drop x xs) == drop (S x) xs","drop (S Z) (drop x xs) == drop (S x) xs","drop (S Z) (drop x xs) == drop (S x) xs","drop (S Z) (drop x xs) == drop (S x) xs","length xs+length xs == length (xs++xs)","length xs+length xs == length (xs++xs)","length xs+length xs == length (xs++xs)","S x+S Z == S (S x)","S Z+S x == S (S x)","S x+S Z == S (S x)","S Z+S x == S (S x)","S x+S Z == S (S x)","S Z+S x == S (S x)","x+S x == S (x+x)","S x+x == S (x+x)","(x+x)+S Z == S (x+x)","S Z+(x+x) == S (x+x)","x+S x == S (x+x)","S x+x == S (x+x)","(x+x)+S Z == S (x+x)","S Z+(x+x) == S (x+x)","x+S x == S (x+x)","S x+x == S (x+x)","(x+x)+S Z == S (x+x)","S Z+(x+x) == S (x+x)","(xs++xs)++xs == xs++(xs++xs)","(xs++xs)++xs == xs++(xs++xs)","(xs++xs)++xs == xs++(xs++xs)","(x+x)+x == x+(x+x)","(x+x)+x == x+(x+x)","(x+x)+x == x+(x+x)"]}}],[91.679615,{"FailedProof":{"prop_name":"elem (z+z) (drop z ys) == elem (z+z) ys"}}],[92.69125,{"FailedProof":{"prop_name":"elem (length xs) (xs++xs) == elem (length xs) xs"}}],[92.691317,{"Discard":{"discarded":["elem (length xs) (xs++xs) == elem (length xs) xs","elem (length xs) (xs++xs) == elem (length xs) xs","elem (x+y) (xs++ys) == elem (x+y) (ys++xs)","elem (x+y) (xs++ys) == elem (x+y) (ys++xs)","elem (x+y) (xs++ys) == elem (x+y) (ys++xs)","elem (x+y) (xs++ys) == elem (x+y) (ys++xs)","elem (x+y) (xs++ys) == elem (x+y) (ys++xs)","elem (x+y) (xs++ys) == elem (x+y) (ys++xs)","elem (x+y) (xs++ys) == elem (x+y) (ys++xs)","elem (x+y) (xs++ys) == elem (x+y) (ys++xs)","drop (x+y) (drop z xs) == drop (x+z) (drop y xs)","drop (x+y) (drop z xs) == drop (z+x) (drop y xs)","drop (x+y) (drop z xs) == drop (x+z) (drop y xs)","drop (x+y) (drop z xs) == drop (z+x) (drop y xs)","drop (x+y) (drop z xs) == drop (x+z) (drop y xs)","drop (x+y) (drop z xs) == drop (z+x) (drop y xs)"]}}],[100.807223,{"FailedProof":{"prop_name":"elem (x+y) (ys++xs) == elem (x+y) (xs++ys)"}}],[108.017549,{"FailedProof":{"prop_name":"drop (y+z) (y:xs) == drop (y+z) (x:xs)"}}],[116.308078,{"FailedProof":{"prop_name":"drop (y+z) (z:xs) == drop (y+z) (x:xs)"}}],[123.469419,{"FailedProof":{"prop_name":"drop (y+z) (Z:xs) == drop (y+z) (x:xs)"}}],[123.469505,{"Discard":{"discarded":["drop (x+y) (x:xs) == drop (x+y) (z:xs)","drop (x+y) (y:xs) == drop (x+y) (z:xs)","drop (x+y) (Z:xs) == drop (x+y) (z:xs)","drop (x+y) (x:xs) == drop (x+y) (z:xs)","drop (x+y) (y:xs) == drop (x+y) (z:xs)","drop (x+y) (Z:xs) == drop (x+y) (z:xs)","drop (x+y) (y:xs) == drop (x+y) (x:xs)","drop (x+y) (Z:xs) == drop (x+y) (x:xs)","drop (x+y) (y:xs) == drop (x+y) (x:xs)","drop (x+y) (Z:xs) == drop (x+y) (x:xs)","drop (x+y) (y:xs) == drop (x+y) (x:xs)","drop (x+y) (Z:xs) == drop (x+y) (x:xs)","drop (x+x) (drop y xs) == drop (x+y) (drop x xs)","drop (x+x) (drop y xs) == drop (x+y) (drop x xs)","drop (x+x) (drop y xs) == drop (x+y) (drop x xs)","drop (x+x) (drop y xs) == drop (y+x) (drop x xs)","drop (x+x) (drop y xs) == drop (y+x) (drop x xs)","drop (x+x) (drop y xs) == drop (y+x) (drop x xs)","drop (x+y) (y:xs) == drop (x+y) (x:xs)","drop (x+y) (Z:xs) == drop (x+y) (x:xs)","drop (x+y) (y:xs) == drop (x+y) (x:xs)","drop (x+y) (Z:xs) == drop (x+y) (x:xs)","drop (x+y) (y:xs) == drop (x+y) (x:xs)","drop (x+y) (Z:xs) == drop (x+y) (x:xs)","drop (x+x) (drop y xs) == drop (x+y) (drop x xs)","drop (x+x) (drop y xs) == drop (x+y) (drop x xs)","drop (x+x) (drop y xs) == drop (x+y) (drop x xs)","drop (x+x) (drop y xs) == drop (y+x) (drop x xs)","drop (x+x) (drop y xs) == drop (y+x) (drop x xs)","drop (x+x) (drop y xs) == drop (y+x) (drop x xs)","drop (x+x) (drop y xs) == drop (x+y) (drop x xs)","drop (x+x) (drop y xs) == drop (x+y) (drop x xs)","drop (x+x) (drop y xs) == drop (x+y) (drop x xs)","drop (x+x) (drop y xs) == drop (y+x) (drop x xs)","drop (x+x) (drop y xs) == drop (y+x) (drop x xs)","drop (x+x) (drop y xs) == drop (y+x) (drop x xs)","(x+y)+(x+z) == (x+z)+(x+y)","(x+y)+(z+z) == (z+x)+(z+y)","(x+x)+(y+z) == (x+y)+(x+z)","(x+y)+(z+z) == (x+z)+(z+y)","(x+y)+(z+x) == (z+x)+(x+y)","(x+x)+(y+z) == (y+x)+(x+z)","length xs+(x+y) == (x+y)+length xs","length xs+(x+y) == (x+y)+length xs","length xs+(x+y) == (x+y)+length xs","(x+y)+S z == (x+z)+S y","(x+y)+S z == (z+x)+S y","S x+(y+z) == (x+y)+S z","S x+(y+z) == (y+x)+S z","S x+(y+z) == (y+z)+S x","(x+y)+(z+y) == (x+z)+(y+y)","(x+y)+(z+y) == (z+x)+(y+y)","(x+x)+(y+z) == (y+z)+(x+x)","length xs+(x+y) == (x+y)+length xs","length xs+(x+y) == (x+y)+length xs","length xs+(x+y) == (x+y)+length xs","length xs+(x+y) == (x+y)+length xs","length xs+(x+y) == (x+y)+length xs","length xs+(x+y) == (x+y)+length xs","elem (length xs) (ys++zs) == elem (length xs) (zs++ys)","elem (length xs) (ys++zs) == elem (length xs) (zs++ys)"]}}],[127.565738,{"FailedProof":{"prop_name":"elem (length xs) (zs++ys) == elem (length xs) (ys++zs)"}}],[131.644038,{"FailedProof":{"prop_name":"elem (S x) (ys++xs) == elem (S x) (xs++ys)"}}],[131.644111,{"Discard":{"discarded":["elem (S x) (xs++ys) == elem (S x) (ys++xs)","elem (S x) (xs++ys) == elem (S x) (ys++xs)","elem (S x) (xs++ys) == elem (S x) (ys++xs)","elem (S x) (xs++ys) == elem (S x) (ys++xs)","elem (S x) (xs++ys) == elem (S x) (ys++xs)","elem (S x) (xs++ys) == elem (S x) (ys++xs)","elem (S x) (xs++ys) == elem (S x) (ys++xs)","elem (S x) (xs++ys) == elem (S x) (ys++xs)","elem (x+x) (xs++ys) == elem (x+x) (ys++xs)","elem (x+x) (xs++ys) == elem (x+x) (ys++xs)","elem (x+x) (xs++ys) == elem (x+x) (ys++xs)","elem (x+x) (xs++ys) == elem (x+x) (ys++xs)","elem (x+x) (xs++ys) == elem (x+x) (ys++xs)","elem (x+x) (xs++ys) == elem (x+x) (ys++xs)","elem (x+x) (xs++ys) == elem (x+x) (ys++xs)","elem (x+x) (xs++ys) == elem (x+x) (ys++xs)","drop (S x) (drop y xs) == drop (S y) (drop x xs)","drop (S x) (drop y xs) == drop (S y) (drop x xs)","drop (S x) (drop y xs) == drop (S y) (drop x xs)","drop (S x) (drop y xs) == drop (S y) (drop x xs)","drop (S x) (drop y xs) == drop (S y) (drop x xs)","drop (S x) (drop y xs) == drop (S y) (drop x xs)","drop (S x) (drop y xs) == drop (S y) (drop x xs)","drop (S x) (drop y xs) == drop (S y) (drop x xs)","drop (S x) (drop y xs) == drop (S y) (drop x xs)","elem x (y:[]) == elem y (x:[])","elem x (y:[]) == elem y (x:[])","elem x (y:[]) == elem y (x:[])","(x:[])++(y:[]) == x:(y:[])","(x:[])++(y:[]) == x:(y:[])","(x:[])++(Z:xs) == x:(Z:xs)","(x:[])++(Z:xs) == x:(Z:xs)","(x:[])++(Z:xs) == x:(Z:xs)","(x:[])++(y:[]) == x:(y:[])","(x:[])++(y:[]) == x:(y:[])","(x:[])++(Z:xs) == x:(Z:xs)","(x:[])++(Z:xs) == x:(Z:xs)","(x:[])++(Z:xs) == x:(Z:xs)","(x:[])++(y:[]) == x:(y:[])","(x:[])++(y:[]) == x:(y:[])","(x:[])++(Z:xs) == x:(Z:xs)","(x:[])++(Z:xs) == x:(Z:xs)","(x:[])++(Z:xs) == x:(Z:xs)","drop (x+x) (y:[]) == drop x (y:[])","drop (x+x) (y:[]) == drop x (y:[])","drop (x+x) (y:[]) == drop x (y:[])","drop (x+x) (y:[]) == drop x (y:[])","drop (x+x) (y:[]) == drop x (y:[])","drop (x+x) (y:[]) == drop x (y:[])"]}}],[135.73993,{"FailedProof":{"prop_name":"elem (x+x) (ys++xs) == elem (x+x) (xs++ys)"}}],[137.777744,{"FailedProof":{"prop_name":"elem Z (ys++xs) == elem Z (xs++ys)"}}],[137.777816,{"Discard":{"discarded":["elem Z (xs++ys) == elem Z (ys++xs)","elem Z (xs++ys) == elem Z (ys++xs)","(Z:xs)++ys == Z:(xs++ys)","(Z:[])++(xs++ys) == Z:(xs++ys)","(Z:xs)++ys == Z:(xs++ys)","(Z:[])++(xs++ys) == Z:(xs++ys)","(Z:xs)++ys == Z:(xs++ys)","(Z:[])++(xs++ys) == Z:(xs++ys)","(Z:xs)++ys == Z:(xs++ys)","(Z:[])++(xs++ys) == Z:(xs++ys)","(Z:xs)++ys == Z:(xs++ys)","(Z:[])++(xs++ys) == Z:(xs++ys)","(Z:xs)++ys == Z:(xs++ys)","(Z:[])++(xs++ys) == Z:(xs++ys)","(Z:[])++(x:xs) == Z:(x:xs)","(Z:[])++(x:xs) == Z:(x:xs)","(Z:[])++(x:xs) == Z:(x:xs)","(Z:[])++(x:xs) == Z:(x:xs)","(Z:[])++(x:xs) == Z:(x:xs)","(Z:[])++(x:xs) == Z:(x:xs)","(Z:[])++(x:xs) == Z:(x:xs)","(Z:[])++(x:xs) == Z:(x:xs)","(Z:[])++(x:xs) == Z:(x:xs)","(Z:[])++drop x xs == Z:drop x xs","(Z:[])++drop x xs == Z:drop x xs","(Z:[])++drop x xs == Z:drop x xs","(Z:[])++drop x xs == Z:drop x xs","(Z:[])++drop x xs == Z:drop x xs","(Z:[])++drop x xs == Z:drop x xs","(Z:[])++drop x xs == Z:drop x xs","(Z:[])++drop x xs == Z:drop x xs","(Z:[])++drop x xs == Z:drop x xs","(x+x)+(y+y) == (x+y)+(x+y)","(x+x)+(y+y) == (y+x)+(y+x)","S x+(x+y) == (x+y)+S x","S x+(y+y) == (y+x)+S y","(x+x)+S y == (x+y)+S x","S x+(y+y) == (x+y)+S y","S x+(y+x) == (y+x)+S x","(x+x)+S y == (y+x)+S x","(x+x)+(x+y) == (x+y)+(x+x)","(x+x)+(y+x) == (y+x)+(x+x)","(x+x)+(y+y) == (x+y)+(x+y)","(x+x)+(y+y) == (y+x)+(y+x)","S x+(x+y) == (x+y)+S x","S x+(y+y) == (y+x)+S y","(x+x)+S y == (x+y)+S x","S x+(y+y) == (x+y)+S y","S x+(y+x) == (y+x)+S x","(x+x)+S y == (y+x)+S x","(x+x)+(x+y) == (x+y)+(x+x)","(x+x)+(y+x) == (y+x)+(x+x)","(x+x)+(y+y) == (x+y)+(x+y)","(x+x)+(y+y) == (y+x)+(y+x)","S x+(x+y) == (x+y)+S x","S x+(y+y) == (y+x)+S y","(x+x)+S y == (x+y)+S x","S x+(y+y) == (x+y)+S y","S x+(y+x) == (y+x)+S x","(x+x)+S y == (y+x)+S x","(x+x)+(x+y) == (x+y)+(x+x)","(x+x)+(y+x) == (y+x)+(x+x)","elem (length xs) (ys++xs) == elem (length xs) (xs++ys)"]}}],[139.827174,{"FailedProof":{"prop_name":"elem (length xs) (ys++xs) == elem (length xs) (xs++ys)"}}],[141.864869,{"FailedProof":{"prop_name":"elem (length ys) (ys++xs) == elem (length ys) (xs++ys)"}}],[141.864936,{"Discard":{"discarded":["elem (length xs) (ys++xs) == elem (length xs) (xs++ys)","elem (length xs) (xs++ys) == elem (length xs) (ys++xs)","elem (length xs) (xs++ys) == elem (length xs) (ys++xs)","elem (x+x) (Z:xs) == elem (x+x) (x:xs)","elem (x+x) (Z:xs) == elem (x+x) (x:xs)","elem (x+x) (Z:xs) == elem (x+x) (x:xs)","elem (x+x) (Z:xs) == elem (x+x) (x:xs)","elem (x+x) (Z:xs) == elem (x+x) (x:xs)","elem (x+x) (Z:xs) == elem (x+x) (x:xs)","elem (x+x) (Z:xs) == elem (x+x) (x:xs)","elem (x+x) (Z:xs) == elem (x+x) (x:xs)","elem (x+x) (Z:xs) == elem (x+x) (x:xs)","drop (x+x) (Z:xs) == drop (x+x) (x:xs)","drop (x+x) (Z:xs) == drop (x+x) (x:xs)","drop (x+x) (Z:xs) == drop (x+x) (x:xs)","drop (x+x) (Z:xs) == drop (x+x) (x:xs)","drop (x+x) (Z:xs) == drop (x+x) (x:xs)","drop (x+x) (Z:xs) == drop (x+x) (x:xs)","drop (x+x) (Z:xs) == drop (x+x) (x:xs)","drop (x+x) (Z:xs) == drop (x+x) (x:xs)","drop (x+x) (Z:xs) == drop (x+x) (x:xs)","S x+length xs == length xs+S x","S x+length xs == length xs+S x","S x+length xs == length xs+S x","(x+x)+length xs == length xs+(x+x)","(x+x)+length xs == length xs+(x+x)","(x+x)+length xs == length xs+(x+x)","S x+length xs == length xs+S x","S x+length xs == length xs+S x","S x+length xs == length xs+S x","(x+x)+length xs == length xs+(x+x)","(x+x)+length xs == length xs+(x+x)","(x+x)+length xs == length xs+(x+x)","S x+length xs == length xs+S x","S x+length xs == length xs+S x","S x+length xs == length xs+S x","(x+x)+length xs == length xs+(x+x)","(x+x)+length xs == length xs+(x+x)","(x+x)+length xs == length xs+(x+x)","S x+S y == S y+S x","S x+S y == S y+S x","S x+S y == S y+S x","(x:[])++(x:[]) == x:(x:[])","(x:[])++(x:[]) == x:(x:[])","(x:[])++(x:[]) == x:(x:[])","drop x (Z:[]) == drop x (x:[])","drop (x+x) (x:[]) == drop x (x:[])","drop (x+x) (Z:[]) == drop x (x:[])","drop x (Z:[]) == drop x (x:[])","drop (x+x) (x:[]) == drop x (x:[])","drop (x+x) (Z:[]) == drop x (x:[])","drop x (Z:[]) == drop x (x:[])","drop (x+x) (x:[]) == drop x (x:[])","drop (x+x) (Z:[]) == drop x (x:[])","(Z:xs)++xs == Z:(xs++xs)","(Z:[])++(xs++xs) == Z:(xs++xs)","(Z:xs)++xs == Z:(xs++xs)","(Z:[])++(xs++xs) == Z:(xs++xs)","(Z:xs)++xs == Z:(xs++xs)","(Z:[])++(xs++xs) == Z:(xs++xs)","(x+x)+S x == S x+(x+x)","(x+x)+S x == S x+(x+x)","(x+x)+S x == S x+(x+x)","elem (S Z) (Z:xs) == elem (S Z) xs","elem (S Z) (xs++xs) == elem (S Z) xs","elem (S Z) (Z:xs) == elem (S Z) xs","elem (S Z) (xs++xs) == elem (S Z) xs","elem (S Z) (Z:xs) == elem (S Z) xs","S Z+S Z == S (S Z)"]}}],[142.88906,{"FailedProof":{"prop_name":"elem (S Z) (xs++xs) == elem (S Z) xs"}}],[146.95509,{"FailedProof":{"prop_name":"elem (y+z) (z:[]) == elem (x+y) (x:[])"}}],[148.981259,{"FailedProof":{"prop_name":"elem y (Z:[]) == elem (x+y) (x:[])"}}],[150.99807,{"FailedProof":{"prop_name":"elem Z (y:[]) == elem (x+y) (x:[])"}}],[153.030504,{"FailedProof":{"prop_name":"elem (y+y) (y:[]) == elem (x+y) (x:[])"}}],[155.040382,{"FailedProof":{"prop_name":"elem (y+y) (Z:[]) == elem (x+y) (x:[])"}}],[155.040448,{"Discard":{"discarded":["elem (x+y) (y:[]) == elem (x+z) (z:[])"]}}],[157.064758,{"FailedProof":{"prop_name":"elem x (Z:[]) == elem (x+y) (y:[])"}}],[159.081267,{"FailedProof":{"prop_name":"elem Z (x:[]) == elem (x+y) (y:[])"}}],[161.12259,{"FailedProof":{"prop_name":"elem (x+x) (x:[]) == elem (x+y) (y:[])"}}],[163.141854,{"FailedProof":{"prop_name":"elem (x+x) (Z:[]) == elem (x+y) (y:[])"}}],[163.142006,{"Discard":{"discarded":["elem x (Z:[]) == elem (y+x) (y:[])","elem Z (x:[]) == elem (y+x) (y:[])","elem (x+x) (x:[]) == elem (y+x) (y:[])","elem (x+x) (Z:[]) == elem (y+x) (y:[])","drop (x+y) (y:[]) == drop (x+y) (x:[])","drop (x+y) (Z:[]) == drop (x+y) (x:[])","drop (x+y) (y:[]) == drop (x+y) (x:[])","drop (x+y) (Z:[]) == drop (x+y) (x:[])","drop (x+y) (y:[]) == drop (x+y) (x:[])","drop (x+y) (Z:[]) == drop (x+y) (x:[])"]}}],[167.247063,{"FailedProof":{"prop_name":"elem (y+z) (y:[]) == elem (x+z) (x:[])"}}],[169.285005,{"FailedProof":{"prop_name":"elem (S Z) (ys++xs) == elem (S Z) (xs++ys)"}}],[169.285064,{"Discard":{"discarded":["elem (S Z) (xs++ys) == elem (S Z) (ys++xs)","elem (S Z) (xs++ys) == elem (S Z) (ys++xs)","(x:[])++(Z:[]) == x:(Z:[])","(x:[])++(Z:[]) == x:(Z:[])","(x:[])++(Z:[]) == x:(Z:[])","(Z:[])++(x:[]) == Z:(x:[])","(Z:[])++(x:[]) == Z:(x:[])","(Z:[])++(x:[]) == Z:(x:[])","(Z:[])++(Z:xs) == Z:(Z:xs)","(Z:[])++(Z:xs) == Z:(Z:xs)","(Z:[])++(Z:xs) == Z:(Z:xs)","(Z:[])++(Z:[]) == Z:(Z:[])"]}}],[169.285672,{"Discard":{"discarded":["length (xs++ys) == length (ys++xs)"]}}],[173.472425,{"FailedProof":{"prop_name":"elem x (ys++xs) == elem x (xs++ys)"}}],[177.504365,{"FailedProof":{"prop_name":"elem x (x:ys) == elem x (x:xs)"}}],[179.535641,{"FailedProof":{"prop_name":"elem x (xs++xs) == elem x xs"}}],[183.796094,{"FailedProof":{"prop_name":"elem y (y:xs) == elem x (x:xs)"}}],[185.820685,{"FailedProof":{"prop_name":"elem y (x:[]) == elem x (y:[])"}}],[187.837382,{"FailedProof":{"prop_name":"elem (S x) (x:xs) == elem (S x) xs"}}],[192.011833,{"FailedProof":{"prop_name":"elem (x+z) (z:[]) == elem (x+y) (y:[])"}}],[194.021579,{"FailedProof":{"prop_name":"elem (x+x) (Z:xs) == elem (x+x) (x:xs)"}}],[195.036842,{"FailedProof":{"prop_name":"elem (S x) (x:[]) == elem x []"}}],[197.080426,{"FailedProof":{"prop_name":"elem (S y) (y:[]) == elem x []"}}],[198.105909,{"FailedProof":{"prop_name":"elem Z (xs++xs) == elem Z xs"}}],[202.160798,{"FailedProof":{"prop_name":"elem (x+y) (xs++xs) == elem (x+y) xs"}}],[206.23139,{"FailedProof":{"prop_name":"elem (y+z) (Z:xs) == elem (y+z) xs"}}],[214.508302,{"FailedProof":{"prop_name":"elem y (y:ys) == elem x (x:xs)"}}],[216.542626,{"FailedProof":{"prop_name":"elem x (x:[]) == elem x (x:xs)"}}],[220.71292,{"FailedProof":{"prop_name":"elem y (y:[]) == elem x (x:xs)"}}],[222.768496,{"FailedProof":{"prop_name":"elem Z (Z:xs) == elem x (x:xs)"}}],[226.789566,{"FailedProof":{"prop_name":"elem Z (Z:ys) == elem x (x:xs)"}}],[228.816042,{"FailedProof":{"prop_name":"elem Z (Z:[]) == elem x (x:xs)"}}],[230.839549,{"FailedProof":{"prop_name":"elem (length xs) (ys++ys) == elem (length xs) ys"}}],[232.868074,{"FailedProof":{"prop_name":"elem (S x) (xs++xs) == elem (S x) xs"}}],[234.890781,{"FailedProof":{"prop_name":"elem (x+x) (xs++xs) == elem (x+x) xs"}}],[236.923576,{"FailedProof":{"prop_name":"elem (z+z) (drop z ys) == elem (z+z) ys"}}],[237.935106,{"FailedProof":{"prop_name":"elem (length xs) (xs++xs) == elem (length xs) xs"}}],[246.046821,{"FailedProof":{"prop_name":"elem (x+y) (ys++xs) == elem (x+y) (xs++ys)"}}],[253.2599,{"FailedProof":{"prop_name":"drop (y+z) (y:xs) == drop (y+z) (x:xs)"}}],[261.479194,{"FailedProof":{"prop_name":"drop (y+z) (z:xs) == drop (y+z) (x:xs)"}}],[268.671753,{"FailedProof":{"prop_name":"drop (y+z) (Z:xs) == drop (y+z) (x:xs)"}}],[272.765616,{"FailedProof":{"prop_name":"elem (length xs) (zs++ys) == elem (length xs) (ys++zs)"}}],[276.845486,{"FailedProof":{"prop_name":"elem (S x) (ys++xs) == elem (S x) (xs++ys)"}}],[281.016559,{"FailedProof":{"prop_name":"elem (x+x) (ys++xs) == elem (x+x) (xs++ys)"}}],[283.053375,{"FailedProof":{"prop_name":"elem Z (ys++xs) == elem Z (xs++ys)"}}],[285.095887,{"FailedProof":{"prop_name":"elem (length xs) (ys++xs) == elem (length xs) (xs++ys)"}}],[287.133128,{"FailedProof":{"prop_name":"elem (length ys) (ys++xs) == elem (length ys) (xs++ys)"}}],[288.152486,{"FailedProof":{"prop_name":"elem (S Z) (xs++xs) == elem (S Z) xs"}}],[292.228667,{"FailedProof":{"prop_name":"elem (y+z) (z:[]) == elem (x+y) (x:[])"}}],[294.257719,{"FailedProof":{"prop_name":"elem y (Z:[]) == elem (x+y) (x:[])"}}],[296.270322,{"FailedProof":{"prop_name":"elem Z (y:[]) == elem (x+y) (x:[])"}}],[298.294346,{"FailedProof":{"prop_name":"elem (y+y) (y:[]) == elem (x+y) (x:[])"}}],[300.311385,{"FailedProof":{"prop_name":"elem (y+y) (Z:[]) == elem (x+y) (x:[])"}}],[302.337296,{"FailedProof":{"prop_name":"elem x (Z:[]) == elem (x+y) (y:[])"}}],[304.354943,{"FailedProof":{"prop_name":"elem Z (x:[]) == elem (x+y) (y:[])"}}],[306.389149,{"FailedProof":{"prop_name":"elem (x+x) (x:[]) == elem (x+y) (y:[])"}}],[308.406581,{"FailedProof":{"prop_name":"elem (x+x) (Z:[]) == elem (x+y) (y:[])"}}],[312.513214,{"FailedProof":{"prop_name":"elem (y+z) (y:[]) == elem (x+z) (x:[])"}}],[314.550438,{"FailedProof":{"prop_name":"elem (S Z) (ys++xs) == elem (S Z) (xs++ys)"}}],[314.550444,{"StartingUserLemmas":[]}],[314.647709,{"PlainProof":{"lemmas":[],"prop_name":"prop_T15"}}],[314.683158,{"PlainProof":{"lemmas":[],"prop_name":"prop_T9"}}],[314.699662,{"PlainProof":{"lemmas":[],"prop_name":"prop_T8"}}],[315.65424,{"InductiveProof":{"lemmas":[],"prop_name":"prop_T1"}}],[316.713447,{"InductiveProof":{"lemmas":[],"prop_name":"prop_T39"}}],[320.802177,{"FailedProof":{"prop_name":"prop_T38"}}],[324.893831,{"FailedProof":{"prop_name":"prop_T37"}}],[327.996021,{"PlainProof":{"lemmas":[],"prop_name":"prop_T24"}}],[328.991858,{"FailedProof":{"prop_name":"prop_T36"}}],[329.020727,{"PlainProof":{"lemmas":[],"prop_name":"prop_T26"}}],[329.020752,{"InductiveProof":{"lemmas":[],"prop_name":"prop_T16"}}],[330.02734,{"InductiveProof":{"lemmas":[],"prop_name":"prop_T13"}}],[334.152024,{"FailedProof":{"prop_name":"prop_T47"}}],[338.249815,{"FailedProof":{"prop_name":"prop_T46"}}],[340.226777,{"FailedProof":{"prop_name":"prop_T45"}}],[344.323268,{"FailedProof":{"prop_name":"prop_T44"}}],[346.343735,{"FailedProof":{"prop_name":"prop_T50"}}],[348.371324,{"FailedProof":{"prop_name":"prop_T49"}}],[349.385762,{"FailedProof":{"prop_name":"prop_T48"}}],[349.411644,{"PlainProof":{"lemmas":[],"prop_name":"prop_T3"}}],[349.437575,{"PlainProof":{"lemmas":[],"prop_name":"prop_T25"}}],[349.458977,{"PlainProof":{"lemmas":[],"prop_name":"prop_T23"}}],[349.485137,{"PlainProof":{"lemmas":[],"prop_name":"prop_T22"}}],[350.394331,{"FailedProof":{"prop_name":"prop_T4"}}],[350.518347,{"PlainProof":{"lemmas":[],"prop_name":"prop_T2"}}],[351.271983,{"InductiveProof":{"lemmas":[],"prop_name":"prop_T20"}}],[353.285115,{"FailedProof":{"prop_name":"prop_T34"}}],[355.298649,{"FailedProof":{"prop_name":"prop_T35"}}],[356.305851,{"FailedProof":{"prop_name":"prop_T33"}}],[357.313209,{"InductiveProof":{"lemmas":[],"prop_name":"prop_T7"}}],[358.327953,{"FailedProof":{"prop_name":"prop_T31"}}],[360.712447,{"FailedProof":{"prop_name":"prop_T6"}}],[360.87694,{"InductiveProof":{"lemmas":[],"prop_name":"prop_T5"}}],[361.891007,{"FailedProof":{"prop_name":"prop_T30"}}],[362.905371,{"FailedProof":{"prop_name":"prop_T29"}}],[363.918697,{"FailedProof":{"prop_name":"prop_T27"}}],[365.946898,{"FailedProof":{"prop_name":"prop_T19"}}],[367.991264,{"FailedProof":{"prop_name":"prop_T17"}}],[368.997697,{"InductiveProof":{"lemmas":[],"prop_name":"prop_T12"}}],[370.011771,{"FailedProof":{"prop_name":"prop_T10"}}],[372.032626,{"FailedProof":{"prop_name":"prop_G6"}}],[373.039401,{"InductiveProof":{"lemmas":[],"prop_name":"prop_G5"}}],[374.053312,{"FailedProof":{"prop_name":"prop_T32"}}],[375.060607,{"InductiveProof":{"lemmas":[],"prop_name":"prop_G9"}}],[376.034041,{"InductiveProof":{"lemmas":[],"prop_name":"prop_T43"}}],[380.146833,{"FailedProof":{"prop_name":"prop_T42"}}],[382.175111,{"FailedProof":{"prop_name":"prop_T41"}}],[383.181738,{"InductiveProof":{"lemmas":[],"prop_name":"prop_T40"}}],[384.194621,{"FailedProof":{"prop_name":"prop_T14"}}],[384.19468,{"Finished":{"proved":["prop_T1","prop_T39","prop_T16","prop_T13","prop_T20","prop_T7","prop_T5","prop_T12","prop_G5","prop_G9","prop_T43","prop_T40","prop_T15","prop_T9","prop_T8","prop_T24","prop_T26","prop_T3","prop_T25","prop_T23","prop_T22","prop_T2"],"unproved":["prop_T38","prop_T37","prop_T36","prop_T47","prop_T46","prop_T45","prop_T44","prop_T50","prop_T49","prop_T48","prop_T4","prop_T34","prop_T35","prop_T33","prop_T31","prop_T6","prop_T30","prop_T29","prop_T27","prop_T19","prop_T17","prop_T10","prop_G6","prop_T32","prop_T42","prop_T41","prop_T14"],"qs_unproved":["elem x (xs++ys) == elem x (ys++xs)","elem x (x:xs) == elem x (x:ys)","elem x (xs++xs) == elem x xs","elem x (x:xs) == elem y (y:xs)","elem x (y:[]) == elem y (x:[])","elem (S x) (x:xs) == elem (S x) xs","elem (x+y) (y:[]) == elem (x+z) (z:[])","elem (x+x) (Z:xs) == elem (x+x) (x:xs)","elem (S x) (x:[]) == elem x []","elem (S x) (x:[]) == elem y []","elem Z (xs++xs) == elem Z xs","elem (x+y) (xs++xs) == elem (x+y) xs","elem (x+y) (Z:xs) == elem (x+y) xs","elem x (x:xs) == elem y (y:ys)","elem x (x:[]) == elem x (x:xs)","elem x (x:[]) == elem y (y:xs)","elem Z (Z:xs) == elem x (x:xs)","elem Z (Z:xs) == elem x (x:ys)","elem Z (Z:[]) == elem x (x:xs)","elem (length xs) (ys++ys) == elem (length xs) ys","elem (S x) (xs++xs) == elem (S x) xs","elem (x+x) (xs++xs) == elem (x+x) xs","elem (x+x) (drop x xs) == elem (x+x) xs","elem (length xs) (xs++xs) == elem (length xs) xs","elem (x+y) (xs++ys) == elem (x+y) (ys++xs)","drop (x+y) (x:xs) == drop (x+y) (z:xs)","drop (x+y) (y:xs) == drop (x+y) (z:xs)","drop (x+y) (Z:xs) == drop (x+y) (z:xs)","elem (length xs) (ys++zs) == elem (length xs) (zs++ys)","elem (S x) (xs++ys) == elem (S x) (ys++xs)","elem (x+x) (xs++ys) == elem (x+x) (ys++xs)","elem Z (xs++ys) == elem Z (ys++xs)","elem (length xs) (ys++xs) == elem (length xs) (xs++ys)","elem (length xs) (xs++ys) == elem (length xs) (ys++xs)","elem (S Z) (xs++xs) == elem (S Z) xs","elem (x+y) (y:[]) == elem (z+x) (z:[])","elem x (Z:[]) == elem (y+x) (y:[])","elem Z (x:[]) == elem (y+x) (y:[])","elem (x+x) (x:[]) == elem (y+x) (y:[])","elem (x+x) (Z:[]) == elem (y+x) (y:[])","elem x (Z:[]) == elem (x+y) (y:[])","elem Z (x:[]) == elem (x+y) (y:[])","elem (x+x) (x:[]) == elem (x+y) (y:[])","elem (x+x) (Z:[]) == elem (x+y) (y:[])","elem (x+y) (x:[]) == elem (z+y) (z:[])","elem (S Z) (xs++ys) == elem (S Z) (ys++xs)"],"qs_proved":["y+x == x+y","xs++[] == xs","drop y (drop x xs) == drop x (drop y xs)","y+(x+z) == x+(y+z)","(xs++ys)++zs == xs++(ys++zs)","drop (x+y) xs == drop x (drop y xs)","drop (length xs) xs == []","drop (x+y) (y:xs) == drop (x+y) (x:xs)","drop (length xs) (xs++ys) == ys","length xs+length ys == length (xs++ys)"]}}]]